Workbook

Sheet Resumen
B2: EVOLTI · INFORME DE COMPRAS
B3: PROYECTO POLARIS 4 — MINIGRANJAS
B4: Tipo de proyecto: Mini Granjas · Exportación de órdenes de compra
B5: Periodo: 2025-10-01 a 2026-08-25 · Generado: 2026-09-21 · Moneda: COP · Cifras calculadas con fórmulas sobre la hoja Detalle
B7: TOTALES DEL PROYECTO
B8: VALOR TOTAL (sin IVA) | D8: =SUM(Detalle!$K$2:$K$326)
B9: IVA | D9: =SUM(Detalle!$M$2:$M$326)
B10: TOTAL CON IVA | D10: =SUM(Detalle!$K$2:$K$326)+SUM(Detalle!$M$2:$M$326)
B12: INDICADORES
B13: Órdenes de compra (No OC únicas) | D13: 106
B14: Líneas de ítem / compras | D14: =COUNTA(Detalle!$K$2:$K$326)
B15: Proveedores distintos | D15: 33
B16: Categorías (Grupos) | D16: 15
B18: GASTO DE OBRA vs ADMINISTRATIVO
B19: Concepto | C19: Valor sin IVA | D19: IVA | E19: Total con IVA
B20: Gasto de obra | C20: =SUMIFS(Detalle!$K$2:$K$326,Detalle!$R$2:$R$326,"<>ADMINISTRATIVO") | D20: =SUMIFS(Detalle!$M$2:$M$326,Detalle!$R$2:$R$326,"<>ADMINISTRATIVO") | E20: =C20+D20
B21: Gasto administrativo | C21: =SUMIFS(Detalle!$K$2:$K$326,Detalle!$R$2:$R$326,"ADMINISTRATIVO") | D21: =SUMIFS(Detalle!$M$2:$M$326,Detalle!$R$2:$R$326,"ADMINISTRATIVO") | E21: =C21+D21
B22: TOTAL | C22: =SUM(C20:C21) | D22: =SUM(D20:D21) | E22: =C22+D22

Sheet Por categoría
B2: GASTO POR CATEGORÍA (GRUPO Y SUBGRUPO)
B3: Cada grupo se abre en sus subgrupos. Los valores son fórmulas SUMAR.SI.CONJUNTO sobre la hoja Detalle.
B5: Grupo | C5: Subgrupo | D5: Valor sin IVA | E5: IVA | F5: Total con IVA | G5: % del total | I5: _grupo | J5: _valor
B6: Servicio | D6: =SUMIFS(Detalle!$K$2:$K$326,Detalle!$F$2:$F$326,$B6) | E6: =SUMIFS(Detalle!$M$2:$M$326,Detalle!$F$2:$F$326,$B6) | F6: =D6+E6 | G6: =IF(SUM(Detalle!$K$2:$K$326)=0,0,D6/SUM(Detalle!$K$2:$K$326)) | I6: =B6 | J6: =D6
C7: Cerramiento Perimetral | D7: =SUMIFS(Detalle!$K$2:$K$326,Detalle!$F$2:$F$326,$B6,Detalle!$G$2:$G$326,$C7) | E7: =SUMIFS(Detalle!$M$2:$M$326,Detalle!$F$2:$F$326,$B6,Detalle!$G$2:$G$326,$C7) | F7: =D7+E7 | G7: =IF(SUM(Detalle!$K$2:$K$326)=0,0,D7/SUM(Detalle!$K$2:$K$326)) | I7: =B18 | J7: =D18
C8: Preparativos Previos Inicio De Obras | D8: =SUMIFS(Detalle!$K$2:$K$326,Detalle!$F$2:$F$326,$B6,Detalle!$G$2:$G$326,$C8) | E8: =SUMIFS(Detalle!$M$2:$M$326,Detalle!$F$2:$F$326,$B6,Detalle!$G$2:$G$326,$C8) | F8: =D8+E8 | G8: =IF(SUM(Detalle!$K$2:$K$326)=0,0,D8/SUM(Detalle!$K$2:$K$326)) | I8: =B20 | J8: =D20
C9: Set (Electrico)Servicio | D9: =SUMIFS(Detalle!$K$2:$K$326,Detalle!$F$2:$F$326,$B6,Detalle!$G$2:$G$326,$C9) | E9: =SUMIFS(Detalle!$M$2:$M$326,Detalle!$F$2:$F$326,$B6,Detalle!$G$2:$G$326,$C9) | F9: =D9+E9 | G9: =IF(SUM(Detalle!$K$2:$K$326)=0,0,D9/SUM(Detalle!$K$2:$K$326)) | I9: =B23 | J9: =D23
C10: Logística Viáticos | D10: =SUMIFS(Detalle!$K$2:$K$326,Detalle!$F$2:$F$326,$B6,Detalle!$G$2:$G$326,$C10) | E10: =SUMIFS(Detalle!$M$2:$M$326,Detalle!$F$2:$F$326,$B6,Detalle!$G$2:$G$326,$C10) | F10: =D10+E10 | G10: =IF(SUM(Detalle!$K$2:$K$326)=0,0,D10/SUM(Detalle!$K$2:$K$326)) | I10: =B25 | J10: =D25
C11: Set (Civil) Servicio | D11: =SUMIFS(Detalle!$K$2:$K$326,Detalle!$F$2:$F$326,$B6,Detalle!$G$2:$G$326,$C11) | E11: =SUMIFS(Detalle!$M$2:$M$326,Detalle!$F$2:$F$326,$B6,Detalle!$G$2:$G$326,$C11) | F11: =D11+E11 | G11: =IF(SUM(Detalle!$K$2:$K$326)=0,0,D11/SUM(Detalle!$K$2:$K$326)) | I11: =B27 | J11: =D27
C12: Descargues | D12: =SUMIFS(Detalle!$K$2:$K$326,Detalle!$F$2:$F$326,$B6,Detalle!$G$2:$G$326,$C12) | E12: =SUMIFS(Detalle!$M$2:$M$326,Detalle!$F$2:$F$326,$B6,Detalle!$G$2:$G$326,$C12) | F12: =D12+E12 | G12: =IF(SUM(Detalle!$K$2:$K$326)=0,0,D12/SUM(Detalle!$K$2:$K$326)) | I12: =B30 | J12: =D30
C13: Baños Portátiles | D13: =SUMIFS(Detalle!$K$2:$K$326,Detalle!$F$2:$F$326,$B6,Detalle!$G$2:$G$326,$C13) | E13: =SUMIFS(Detalle!$M$2:$M$326,Detalle!$F$2:$F$326,$B6,Detalle!$G$2:$G$326,$C13) | F13: =D13+E13 | G13: =IF(SUM(Detalle!$K$2:$K$326)=0,0,D13/SUM(Detalle!$K$2:$K$326)) | I13: =B33 | J13: =D33
C14: Upme | D14: =SUMIFS(Detalle!$K$2:$K$326,Detalle!$F$2:$F$326,$B6,Detalle!$G$2:$G$326,$C14) | E14: =SUMIFS(Detalle!$M$2:$M$326,Detalle!$F$2:$F$326,$B6,Detalle!$G$2:$G$326,$C14) | F14: =D14+E14 | G14: =IF(SUM(Detalle!$K$2:$K$326)=0,0,D14/SUM(Detalle!$K$2:$K$326)) | I14: =B36 | J14: =D36
C15: Transportes | D15: =SUMIFS(Detalle!$K$2:$K$326,Detalle!$F$2:$F$326,$B6,Detalle!$G$2:$G$326,$C15) | E15: =SUMIFS(Detalle!$M$2:$M$326,Detalle!$F$2:$F$326,$B6,Detalle!$G$2:$G$326,$C15) | F15: =D15+E15 | G15: =IF(SUM(Detalle!$K$2:$K$326)=0,0,D15/SUM(Detalle!$K$2:$K$326)) | I15: =B38 | J15: =D38
C16: Retie | D16: =SUMIFS(Detalle!$K$2:$K$326,Detalle!$F$2:$F$326,$B6,Detalle!$G$2:$G$326,$C16) | E16: =SUMIFS(Detalle!$M$2:$M$326,Detalle!$F$2:$F$326,$B6,Detalle!$G$2:$G$326,$C16) | F16: =D16+E16 | G16: =IF(SUM(Detalle!$K$2:$K$326)=0,0,D16/SUM(Detalle!$K$2:$K$326)) | I16: =B41 | J16: =D41
C17: (Sin Subgrupo) | D17: =SUMIFS(Detalle!$K$2:$K$326,Detalle!$F$2:$F$326,$B6,Detalle!$G$2:$G$326,$C17) | E17: =SUMIFS(Detalle!$M$2:$M$326,Detalle!$F$2:$F$326,$B6,Detalle!$G$2:$G$326,$C17) | F17: =D17+E17 | G17: =IF(SUM(Detalle!$K$2:$K$326)=0,0,D17/SUM(Detalle!$K$2:$K$326)) | I17: =B43 | J17: =D43
B18: C. Estructura Solar | D18: =SUMIFS(Detalle!$K$2:$K$326,Detalle!$F$2:$F$326,$B18) | E18: =SUMIFS(Detalle!$M$2:$M$326,Detalle!$F$2:$F$326,$B18) | F18: =D18+E18 | G18: =IF(SUM(Detalle!$K$2:$K$326)=0,0,D18/SUM(Detalle!$K$2:$K$326)) | I18: =B45 | J18: =D45
C19: (Sin Subgrupo) | D19: =SUMIFS(Detalle!$K$2:$K$326,Detalle!$F$2:$F$326,$B18,Detalle!$G$2:$G$326,$C19) | E19: =SUMIFS(Detalle!$M$2:$M$326,Detalle!$F$2:$F$326,$B18,Detalle!$G$2:$G$326,$C19) | F19: =D19+E19 | G19: =IF(SUM(Detalle!$K$2:$K$326)=0,0,D19/SUM(Detalle!$K$2:$K$326)) | I19: =B47 | J19: =D47
B20: Set (Electrico) Suministro | D20: =SUMIFS(Detalle!$K$2:$K$326,Detalle!$F$2:$F$326,$B20) | E20: =SUMIFS(Detalle!$M$2:$M$326,Detalle!$F$2:$F$326,$B20) | F20: =D20+E20 | G20: =IF(SUM(Detalle!$K$2:$K$326)=0,0,D20/SUM(Detalle!$K$2:$K$326)) | I20: =B49 | J20: =D49
C21: (Sin Subgrupo) | D21: =SUMIFS(Detalle!$K$2:$K$326,Detalle!$F$2:$F$326,$B20,Detalle!$G$2:$G$326,$C21) | E21: =SUMIFS(Detalle!$M$2:$M$326,Detalle!$F$2:$F$326,$B20,Detalle!$G$2:$G$326,$C21) | F21: =D21+E21 | G21: =IF(SUM(Detalle!$K$2:$K$326)=0,0,D21/SUM(Detalle!$K$2:$K$326))
C22: Set (Electrico)Servicio | D22: =SUMIFS(Detalle!$K$2:$K$326,Detalle!$F$2:$F$326,$B20,Detalle!$G$2:$G$326,$C22) | E22: =SUMIFS(Detalle!$M$2:$M$326,Detalle!$F$2:$F$326,$B20,Detalle!$G$2:$G$326,$C22) | F22: =D22+E22 | G22: =IF(SUM(Detalle!$K$2:$K$326)=0,0,D22/SUM(Detalle!$K$2:$K$326))
B23: C. Inversores | D23: =SUMIFS(Detalle!$K$2:$K$326,Detalle!$F$2:$F$326,$B23) | E23: =SUMIFS(Detalle!$M$2:$M$326,Detalle!$F$2:$F$326,$B23) | F23: =D23+E23 | G23: =IF(SUM(Detalle!$K$2:$K$326)=0,0,D23/SUM(Detalle!$K$2:$K$326))
C24: (Sin Subgrupo) | D24: =SUMIFS(Detalle!$K$2:$K$326,Detalle!$F$2:$F$326,$B23,Detalle!$G$2:$G$326,$C24) | E24: =SUMIFS(Detalle!$M$2:$M$326,Detalle!$F$2:$F$326,$B23,Detalle!$G$2:$G$326,$C24) | F24: =D24+E24 | G24: =IF(SUM(Detalle!$K$2:$K$326)=0,0,D24/SUM(Detalle!$K$2:$K$326))
B25: C. Material Micropilotaje | D25: =SUMIFS(Detalle!$K$2:$K$326,Detalle!$F$2:$F$326,$B25) | E25: =SUMIFS(Detalle!$M$2:$M$326,Detalle!$F$2:$F$326,$B25) | F25: =D25+E25 | G25: =IF(SUM(Detalle!$K$2:$K$326)=0,0,D25/SUM(Detalle!$K$2:$K$326))
C26: (Sin Subgrupo) | D26: =SUMIFS(Detalle!$K$2:$K$326,Detalle!$F$2:$F$326,$B25,Detalle!$G$2:$G$326,$C26) | E26: =SUMIFS(Detalle!$M$2:$M$326,Detalle!$F$2:$F$326,$B25,Detalle!$G$2:$G$326,$C26) | F26: =D26+E26 | G26: =IF(SUM(Detalle!$K$2:$K$326)=0,0,D26/SUM(Detalle!$K$2:$K$326))
B27: Set (Civil) Suministro | D27: =SUMIFS(Detalle!$K$2:$K$326,Detalle!$F$2:$F$326,$B27) | E27: =SUMIFS(Detalle!$M$2:$M$326,Detalle!$F$2:$F$326,$B27) | F27: =D27+E27 | G27: =IF(SUM(Detalle!$K$2:$K$326)=0,0,D27/SUM(Detalle!$K$2:$K$326))
C28: Set (Civil) Servicio | D28: =SUMIFS(Detalle!$K$2:$K$326,Detalle!$F$2:$F$326,$B27,Detalle!$G$2:$G$326,$C28) | E28: =SUMIFS(Detalle!$M$2:$M$326,Detalle!$F$2:$F$326,$B27,Detalle!$G$2:$G$326,$C28) | F28: =D28+E28 | G28: =IF(SUM(Detalle!$K$2:$K$326)=0,0,D28/SUM(Detalle!$K$2:$K$326))
C29: (Sin Subgrupo) | D29: =SUMIFS(Detalle!$K$2:$K$326,Detalle!$F$2:$F$326,$B27,Detalle!$G$2:$G$326,$C29) | E29: =SUMIFS(Detalle!$M$2:$M$326,Detalle!$F$2:$F$326,$B27,Detalle!$G$2:$G$326,$C29) | F29: =D29+E29 | G29: =IF(SUM(Detalle!$K$2:$K$326)=0,0,D29/SUM(Detalle!$K$2:$K$326))
B30: Cajas De Paso | D30: =SUMIFS(Detalle!$K$2:$K$326,Detalle!$F$2:$F$326,$B30) | E30: =SUMIFS(Detalle!$M$2:$M$326,Detalle!$F$2:$F$326,$B30) | F30: =D30+E30 | G30: =IF(SUM(Detalle!$K$2:$K$326)=0,0,D30/SUM(Detalle!$K$2:$K$326))
C31: (Sin Subgrupo) | D31: =SUMIFS(Detalle!$K$2:$K$326,Detalle!$F$2:$F$326,$B30,Detalle!$G$2:$G$326,$C31) | E31: =SUMIFS(Detalle!$M$2:$M$326,Detalle!$F$2:$F$326,$B30,Detalle!$G$2:$G$326,$C31) | F31: =D31+E31 | G31: =IF(SUM(Detalle!$K$2:$K$326)=0,0,D31/SUM(Detalle!$K$2:$K$326))
C32: Transportes | D32: =SUMIFS(Detalle!$K$2:$K$326,Detalle!$F$2:$F$326,$B30,Detalle!$G$2:$G$326,$C32) | E32: =SUMIFS(Detalle!$M$2:$M$326,Detalle!$F$2:$F$326,$B30,Detalle!$G$2:$G$326,$C32) | F32: =D32+E32 | G32: =IF(SUM(Detalle!$K$2:$K$326)=0,0,D32/SUM(Detalle!$K$2:$K$326))
B33: Montaje Eléctrico | D33: =SUMIFS(Detalle!$K$2:$K$326,Detalle!$F$2:$F$326,$B33) | E33: =SUMIFS(Detalle!$M$2:$M$326,Detalle!$F$2:$F$326,$B33) | F33: =D33+E33 | G33: =IF(SUM(Detalle!$K$2:$K$326)=0,0,D33/SUM(Detalle!$K$2:$K$326))
C34: Set (Electrico)Servicio | D34: =SUMIFS(Detalle!$K$2:$K$326,Detalle!$F$2:$F$326,$B33,Detalle!$G$2:$G$326,$C34) | E34: =SUMIFS(Detalle!$M$2:$M$326,Detalle!$F$2:$F$326,$B33,Detalle!$G$2:$G$326,$C34) | F34: =D34+E34 | G34: =IF(SUM(Detalle!$K$2:$K$326)=0,0,D34/SUM(Detalle!$K$2:$K$326))
C35: (Sin Subgrupo) | D35: =SUMIFS(Detalle!$K$2:$K$326,Detalle!$F$2:$F$326,$B33,Detalle!$G$2:$G$326,$C35) | E35: =SUMIFS(Detalle!$M$2:$M$326,Detalle!$F$2:$F$326,$B33,Detalle!$G$2:$G$326,$C35) | F35: =D35+E35 | G35: =IF(SUM(Detalle!$K$2:$K$326)=0,0,D35/SUM(Detalle!$K$2:$K$326))
B36: Gastos Administrativos | D36: =SUMIFS(Detalle!$K$2:$K$326,Detalle!$F$2:$F$326,$B36) | E36: =SUMIFS(Detalle!$M$2:$M$326,Detalle!$F$2:$F$326,$B36) | F36: =D36+E36 | G36: =IF(SUM(Detalle!$K$2:$K$326)=0,0,D36/SUM(Detalle!$K$2:$K$326))
C37: Logística Viáticos | D37: =SUMIFS(Detalle!$K$2:$K$326,Detalle!$F$2:$F$326,$B36,Detalle!$G$2:$G$326,$C37) | E37: =SUMIFS(Detalle!$M$2:$M$326,Detalle!$F$2:$F$326,$B36,Detalle!$G$2:$G$326,$C37) | F37: =D37+E37 | G37: =IF(SUM(Detalle!$K$2:$K$326)=0,0,D37/SUM(Detalle!$K$2:$K$326))
B38: C. Canalizaciones | D38: =SUMIFS(Detalle!$K$2:$K$326,Detalle!$F$2:$F$326,$B38) | E38: =SUMIFS(Detalle!$M$2:$M$326,Detalle!$F$2:$F$326,$B38) | F38: =D38+E38 | G38: =IF(SUM(Detalle!$K$2:$K$326)=0,0,D38/SUM(Detalle!$K$2:$K$326))
C39: (Sin Subgrupo) | D39: =SUMIFS(Detalle!$K$2:$K$326,Detalle!$F$2:$F$326,$B38,Detalle!$G$2:$G$326,$C39) | E39: =SUMIFS(Detalle!$M$2:$M$326,Detalle!$F$2:$F$326,$B38,Detalle!$G$2:$G$326,$C39) | F39: =D39+E39 | G39: =IF(SUM(Detalle!$K$2:$K$326)=0,0,D39/SUM(Detalle!$K$2:$K$326))
C40: Instalación De Tuberías Ac, Dc Y Tierra | D40: =SUMIFS(Detalle!$K$2:$K$326,Detalle!$F$2:$F$326,$B38,Detalle!$G$2:$G$326,$C40) | E40: =SUMIFS(Detalle!$M$2:$M$326,Detalle!$F$2:$F$326,$B38,Detalle!$G$2:$G$326,$C40) | F40: =D40+E40 | G40: =IF(SUM(Detalle!$K$2:$K$326)=0,0,D40/SUM(Detalle!$K$2:$K$326))
B41: Armado Mesas Fv | D41: =SUMIFS(Detalle!$K$2:$K$326,Detalle!$F$2:$F$326,$B41) | E41: =SUMIFS(Detalle!$M$2:$M$326,Detalle!$F$2:$F$326,$B41) | F41: =D41+E41 | G41: =IF(SUM(Detalle!$K$2:$K$326)=0,0,D41/SUM(Detalle!$K$2:$K$326))
C42: (Sin Subgrupo) | D42: =SUMIFS(Detalle!$K$2:$K$326,Detalle!$F$2:$F$326,$B41,Detalle!$G$2:$G$326,$C42) | E42: =SUMIFS(Detalle!$M$2:$M$326,Detalle!$F$2:$F$326,$B41,Detalle!$G$2:$G$326,$C42) | F42: =D42+E42 | G42: =IF(SUM(Detalle!$K$2:$K$326)=0,0,D42/SUM(Detalle!$K$2:$K$326))
B43: 9-Legalización | D43: =SUMIFS(Detalle!$K$2:$K$326,Detalle!$F$2:$F$326,$B43) | E43: =SUMIFS(Detalle!$M$2:$M$326,Detalle!$F$2:$F$326,$B43) | F43: =D43+E43 | G43: =IF(SUM(Detalle!$K$2:$K$326)=0,0,D43/SUM(Detalle!$K$2:$K$326))
C44: 9.1 -Retie Gd | D44: =SUMIFS(Detalle!$K$2:$K$326,Detalle!$F$2:$F$326,$B43,Detalle!$G$2:$G$326,$C44) | E44: =SUMIFS(Detalle!$M$2:$M$326,Detalle!$F$2:$F$326,$B43,Detalle!$G$2:$G$326,$C44) | F44: =D44+E44 | G44: =IF(SUM(Detalle!$K$2:$K$326)=0,0,D44/SUM(Detalle!$K$2:$K$326))
B45: C. Cableado Ac | D45: =SUMIFS(Detalle!$K$2:$K$326,Detalle!$F$2:$F$326,$B45) | E45: =SUMIFS(Detalle!$M$2:$M$326,Detalle!$F$2:$F$326,$B45) | F45: =D45+E45 | G45: =IF(SUM(Detalle!$K$2:$K$326)=0,0,D45/SUM(Detalle!$K$2:$K$326))
C46: (Sin Subgrupo) | D46: =SUMIFS(Detalle!$K$2:$K$326,Detalle!$F$2:$F$326,$B45,Detalle!$G$2:$G$326,$C46) | E46: =SUMIFS(Detalle!$M$2:$M$326,Detalle!$F$2:$F$326,$B45,Detalle!$G$2:$G$326,$C46) | F46: =D46+E46 | G46: =IF(SUM(Detalle!$K$2:$K$326)=0,0,D46/SUM(Detalle!$K$2:$K$326))
B47: C. Cableado Dc | D47: =SUMIFS(Detalle!$K$2:$K$326,Detalle!$F$2:$F$326,$B47) | E47: =SUMIFS(Detalle!$M$2:$M$326,Detalle!$F$2:$F$326,$B47) | F47: =D47+E47 | G47: =IF(SUM(Detalle!$K$2:$K$326)=0,0,D47/SUM(Detalle!$K$2:$K$326))
C48: (Sin Subgrupo) | D48: =SUMIFS(Detalle!$K$2:$K$326,Detalle!$F$2:$F$326,$B47,Detalle!$G$2:$G$326,$C48) | E48: =SUMIFS(Detalle!$M$2:$M$326,Detalle!$F$2:$F$326,$B47,Detalle!$G$2:$G$326,$C48) | F48: =D48+E48 | G48: =IF(SUM(Detalle!$K$2:$K$326)=0,0,D48/SUM(Detalle!$K$2:$K$326))
B49: C. Cableado Tierra | D49: =SUMIFS(Detalle!$K$2:$K$326,Detalle!$F$2:$F$326,$B49) | E49: =SUMIFS(Detalle!$M$2:$M$326,Detalle!$F$2:$F$326,$B49) | F49: =D49+E49 | G49: =IF(SUM(Detalle!$K$2:$K$326)=0,0,D49/SUM(Detalle!$K$2:$K$326))
C50: (Sin Subgrupo) | D50: =SUMIFS(Detalle!$K$2:$K$326,Detalle!$F$2:$F$326,$B49,Detalle!$G$2:$G$326,$C50) | E50: =SUMIFS(Detalle!$M$2:$M$326,Detalle!$F$2:$F$326,$B49,Detalle!$G$2:$G$326,$C50) | F50: =D50+E50 | G50: =IF(SUM(Detalle!$K$2:$K$326)=0,0,D50/SUM(Detalle!$K$2:$K$326))
B51: TOTAL | D51: =SUM(Detalle!$K$2:$K$326) | E51: =SUM(Detalle!$M$2:$M$326) | F51: =D51+E51 | G51: 1

Sheet Por tipo de ítem
B2: ¿QUÉ SE COMPRÓ? — CATEGORIZACIÓN DE ÍTEMS
B3: Los ítems se agrupan por tipo (transformadores, medidores, inversores, cable, etc.). Se muestra la cantidad total y el valor. Cantidades y valores son fórmulas sobre la hoja Detalle.
B5: RESUMEN POR CATEGORÍA
B6: Categoría de ítem | C6: Cant. total | D6: Valor sin IVA | E6: IVA | F6: Total con IVA | G6: % del total
B7: Estructura y soportería solar | C7: =SUMIFS(Detalle!$I$2:$I$326,Detalle!$T$2:$T$326,$B7) | D7: =SUMIFS(Detalle!$K$2:$K$326,Detalle!$T$2:$T$326,$B7) | E7: =SUMIFS(Detalle!$M$2:$M$326,Detalle!$T$2:$T$326,$B7) | F7: =D7+E7 | G7: =IF(SUM(Detalle!$K$2:$K$326)=0,0,D7/SUM(Detalle!$K$2:$K$326))
B8: Cerramiento perimetral | C8: =SUMIFS(Detalle!$I$2:$I$326,Detalle!$T$2:$T$326,$B8) | D8: =SUMIFS(Detalle!$K$2:$K$326,Detalle!$T$2:$T$326,$B8) | E8: =SUMIFS(Detalle!$M$2:$M$326,Detalle!$T$2:$T$326,$B8) | F8: =D8+E8 | G8: =IF(SUM(Detalle!$K$2:$K$326)=0,0,D8/SUM(Detalle!$K$2:$K$326))
B9: Obra civil (concreto, agregados) | C9: =SUMIFS(Detalle!$I$2:$I$326,Detalle!$T$2:$T$326,$B9) | D9: =SUMIFS(Detalle!$K$2:$K$326,Detalle!$T$2:$T$326,$B9) | E9: =SUMIFS(Detalle!$M$2:$M$326,Detalle!$T$2:$T$326,$B9) | F9: =D9+E9 | G9: =IF(SUM(Detalle!$K$2:$K$326)=0,0,D9/SUM(Detalle!$K$2:$K$326))
B10: Inversores | C10: =SUMIFS(Detalle!$I$2:$I$326,Detalle!$T$2:$T$326,$B10) | D10: =SUMIFS(Detalle!$K$2:$K$326,Detalle!$T$2:$T$326,$B10) | E10: =SUMIFS(Detalle!$M$2:$M$326,Detalle!$T$2:$T$326,$B10) | F10: =D10+E10 | G10: =IF(SUM(Detalle!$K$2:$K$326)=0,0,D10/SUM(Detalle!$K$2:$K$326))
B11: Cableado y conductores | C11: =SUMIFS(Detalle!$I$2:$I$326,Detalle!$T$2:$T$326,$B11) | D11: =SUMIFS(Detalle!$K$2:$K$326,Detalle!$T$2:$T$326,$B11) | E11: =SUMIFS(Detalle!$M$2:$M$326,Detalle!$T$2:$T$326,$B11) | F11: =D11+E11 | G11: =IF(SUM(Detalle!$K$2:$K$326)=0,0,D11/SUM(Detalle!$K$2:$K$326))
B12: Servicios de obra e ingeniería | C12: =SUMIFS(Detalle!$I$2:$I$326,Detalle!$T$2:$T$326,$B12) | D12: =SUMIFS(Detalle!$K$2:$K$326,Detalle!$T$2:$T$326,$B12) | E12: =SUMIFS(Detalle!$M$2:$M$326,Detalle!$T$2:$T$326,$B12) | F12: =D12+E12 | G12: =IF(SUM(Detalle!$K$2:$K$326)=0,0,D12/SUM(Detalle!$K$2:$K$326))
B13: Alquiler de maquinaria y equipos | C13: =SUMIFS(Detalle!$I$2:$I$326,Detalle!$T$2:$T$326,$B13) | D13: =SUMIFS(Detalle!$K$2:$K$326,Detalle!$T$2:$T$326,$B13) | E13: =SUMIFS(Detalle!$M$2:$M$326,Detalle!$T$2:$T$326,$B13) | F13: =D13+E13 | G13: =IF(SUM(Detalle!$K$2:$K$326)=0,0,D13/SUM(Detalle!$K$2:$K$326))
B14: RETIE / Legalización / Medición | C14: =SUMIFS(Detalle!$I$2:$I$326,Detalle!$T$2:$T$326,$B14) | D14: =SUMIFS(Detalle!$K$2:$K$326,Detalle!$T$2:$T$326,$B14) | E14: =SUMIFS(Detalle!$M$2:$M$326,Detalle!$T$2:$T$326,$B14) | F14: =D14+E14 | G14: =IF(SUM(Detalle!$K$2:$K$326)=0,0,D14/SUM(Detalle!$K$2:$K$326))
B15: Viáticos - Alimentación | C15: =SUMIFS(Detalle!$I$2:$I$326,Detalle!$T$2:$T$326,$B15) | D15: =SUMIFS(Detalle!$K$2:$K$326,Detalle!$T$2:$T$326,$B15) | E15: =SUMIFS(Detalle!$M$2:$M$326,Detalle!$T$2:$T$326,$B15) | F15: =D15+E15 | G15: =IF(SUM(Detalle!$K$2:$K$326)=0,0,D15/SUM(Detalle!$K$2:$K$326))
B16: Fletes y transporte de carga | C16: =SUMIFS(Detalle!$I$2:$I$326,Detalle!$T$2:$T$326,$B16) | D16: =SUMIFS(Detalle!$K$2:$K$326,Detalle!$T$2:$T$326,$B16) | E16: =SUMIFS(Detalle!$M$2:$M$326,Detalle!$T$2:$T$326,$B16) | F16: =D16+E16 | G16: =IF(SUM(Detalle!$K$2:$K$326)=0,0,D16/SUM(Detalle!$K$2:$K$326))
B17: Viáticos - Hospedaje | C17: =SUMIFS(Detalle!$I$2:$I$326,Detalle!$T$2:$T$326,$B17) | D17: =SUMIFS(Detalle!$K$2:$K$326,Detalle!$T$2:$T$326,$B17) | E17: =SUMIFS(Detalle!$M$2:$M$326,Detalle!$T$2:$T$326,$B17) | F17: =D17+E17 | G17: =IF(SUM(Detalle!$K$2:$K$326)=0,0,D17/SUM(Detalle!$K$2:$K$326))
B18: Canalización y tubería | C18: =SUMIFS(Detalle!$I$2:$I$326,Detalle!$T$2:$T$326,$B18) | D18: =SUMIFS(Detalle!$K$2:$K$326,Detalle!$T$2:$T$326,$B18) | E18: =SUMIFS(Detalle!$M$2:$M$326,Detalle!$T$2:$T$326,$B18) | F18: =D18+E18 | G18: =IF(SUM(Detalle!$K$2:$K$326)=0,0,D18/SUM(Detalle!$K$2:$K$326))
... B32: Tableros y protecciones | C32: =SUMIFS(Detalle!$I$2:$I$326,Detalle!$T$2:$T$326,$B32) | D32: =SUMIFS(Detalle!$K$2:$K$326,Detalle!$T$2:$T$326,$B32) | E32: =SUMIFS(Detalle!$M$2:$M$326,Detalle!$T$2:$T$326,$B32) | F32: =D32+E32 | G32: =IF(SUM(Detalle!$K$2:$K$326)=0,0,D32/SUM(Detalle!$K$2:$K$326))
B33: TOTAL | C33: =SUM(C7:C32) | D33: =SUM(Detalle!$K$2:$K$326) | E33: =SUM(Detalle!$M$2:$M$326) | F33: =D33+E33 | G33: 1
B36: DETALLE DE ÍTEMS POR CATEGORÍA
B37: Aquí se ve, por ejemplo, cuántos transformadores, medidores o inversores consumió el proyecto.
B38: Categoría / Ítem | C38: Cant. | D38: Valor sin IVA | E38: IVA | F38: Total con IVA
B39: Estructura y soportería solar | C39: =SUMIFS(Detalle!$I$2:$I$326,Detalle!$T$2:$T$326,$B39) | D39: =SUMIFS(Detalle!$K$2:$K$326,Detalle!$T$2:$T$326,$B39) | E39: =SUMIFS(Detalle!$M$2:$M$326,Detalle!$T$2:$T$326,$B39) | F39: =D39+E39
B40: ESTRUCTURA SOLAR TIPO GRANJA - TIPO DE MESA 2PV14 PARA 28 PANELES - UND | C40: =SUMIFS(Detalle!$I$2:$I$326,Detalle!$T$2:$T$326,$B39,Detalle!$H$2:$H$326,$B40) | D40: =SUMIFS(Detalle!$K$2:$K$326,Detalle!$T$2:$T$326,$B39,Detalle!$H$2:$H$326,$B40) | E40: =SUMIFS(Detalle!$M$2:$M$326,Detalle!$T$2:$T$326,$B39,Detalle!$H$2:$H$326,$B40) | F40: =D40+E40
B41: SUMINISTRO DE ESTRUCTURA METALICA PARA TECHO SUBESTACION. MATERIALES: 6 COLUMNAS EN TUBO CUADRADO 100 X 100 EN 4MM, 3 VIGAS EN TUBO RECTANGULAR DE 100 X 50 EN 2 MM, CORREAS EN PHR 120 X 60 EN 1.5 MM, RIDIGIZADORES EN PLATINA DE 3/4 X 3 /16, CANAL EN - UND | C41: =SUMIFS(Detalle!$I$2:$I$326,Detalle!$T$2:$T$326,$B39,Detalle!$H$2:$H$326,$B41) | D41: =SUMIFS(Detalle!$K$2:$K$326,Detalle!$T$2:$T$326,$B39,Detalle!$H$2:$H$326,$B41) | E41: =SUMIFS(Detalle!$M$2:$M$326,Detalle!$T$2:$T$326,$B39,Detalle!$H$2:$H$326,$B41) | F41: =D41+E41
B42: SUMINISTRO DE MARCOS METÁLICOS DE 1.40X1.40 MTS EN ANGULO DE 1 1/2X3/16" - UND | C42: =SUMIFS(Detalle!$I$2:$I$326,Detalle!$T$2:$T$326,$B39,Detalle!$H$2:$H$326,$B42) | D42: =SUMIFS(Detalle!$K$2:$K$326,Detalle!$T$2:$T$326,$B39,Detalle!$H$2:$H$326,$B42) | E42: =SUMIFS(Detalle!$M$2:$M$326,Detalle!$T$2:$T$326,$B39,Detalle!$H$2:$H$326,$B42) | F42: =D42+E42
B43: SUMINISTRO DE TAPAS PARA CÁRCAMOS. CUARTO ELÉCTRICO. EN ANGULO DE 1 1/4X1/8" Y LAMINA ALFAJOR DE 2.5MM, PINTURA ANTICORROSIVA Y ESMALTE. - UND | C43: =SUMIFS(Detalle!$I$2:$I$326,Detalle!$T$2:$T$326,$B39,Detalle!$H$2:$H$326,$B43) | D43: =SUMIFS(Detalle!$K$2:$K$326,Detalle!$T$2:$T$326,$B39,Detalle!$H$2:$H$326,$B43) | E43: =SUMIFS(Detalle!$M$2:$M$326,Detalle!$T$2:$T$326,$B39,Detalle!$H$2:$H$326,$B43) | F43: =D43+E43
B44: SUPERBOARD ESTANDAR 1220X2440X6MM (DP) UND SUPERBOAR - UND | C44: =SUMIFS(Detalle!$I$2:$I$326,Detalle!$T$2:$T$326,$B39,Detalle!$H$2:$H$326,$B44) | D44: =SUMIFS(Detalle!$K$2:$K$326,Detalle!$T$2:$T$326,$B39,Detalle!$H$2:$H$326,$B44) | E44: =SUMIFS(Detalle!$M$2:$M$326,Detalle!$T$2:$T$326,$B39,Detalle!$H$2:$H$326,$B44) | F44: =D44+E44
B45: PERFIL RECTANGULAR DE 2"X1" X 6M CAL 18 - UND | C45: =SUMIFS(Detalle!$I$2:$I$326,Detalle!$T$2:$T$326,$B39,Detalle!$H$2:$H$326,$B45) | D45: =SUMIFS(Detalle!$K$2:$K$326,Detalle!$T$2:$T$326,$B39,Detalle!$H$2:$H$326,$B45) | E45: =SUMIFS(Detalle!$M$2:$M$326,Detalle!$T$2:$T$326,$B39,Detalle!$H$2:$H$326,$B45) | F45: =D45+E45
B46: PLATINA DE 35CMX35CMX1CM - UND | C46: =SUMIFS(Detalle!$I$2:$I$326,Detalle!$T$2:$T$326,$B39,Detalle!$H$2:$H$326,$B46) | D46: =SUMIFS(Detalle!$K$2:$K$326,Detalle!$T$2:$T$326,$B39,Detalle!$H$2:$H$326,$B46) | E46: =SUMIFS(Detalle!$M$2:$M$326,Detalle!$T$2:$T$326,$B39,Detalle!$H$2:$H$326,$B46) | F46: =D46+E46
B47: RIEL CHANNEL 4X2 RANURADO 3M - UND | C47: =SUMIFS(Detalle!$I$2:$I$326,Detalle!$T$2:$T$326,$B39,Detalle!$H$2:$H$326,$B47) | D47: =SUMIFS(Detalle!$K$2:$K$326,Detalle!$T$2:$T$326,$B39,Detalle!$H$2:$H$326,$B47) | E47: =SUMIFS(Detalle!$M$2:$M$326,Detalle!$T$2:$T$326,$B39,Detalle!$H$2:$H$326,$B47) | F47: =D47+E47
B48: MINIBREAKER BIPOLAR PARA RIEL 6AMP SIEMENS - UND | C48: =SUMIFS(Detalle!$I$2:$I$326,Detalle!$T$2:$T$326,$B39,Detalle!$H$2:$H$326,$B48) | D48: =SUMIFS(Detalle!$K$2:$K$326,Detalle!$T$2:$T$326,$B39,Detalle!$H$2:$H$326,$B48) | E48: =SUMIFS(Detalle!$M$2:$M$326,Detalle!$T$2:$T$326,$B39,Detalle!$H$2:$H$326,$B48) | F48: =D48+E48
B49: VIGUETA PARA SUPERBOARD DE 1 1/2" X3/4" CALIBRE 40 - UND | C49: =SUMIFS(Detalle!$I$2:$I$326,Detalle!$T$2:$T$326,$B39,Detalle!$H$2:$H$326,$B49) | D49: =SUMIFS(Detalle!$K$2:$K$326,Detalle!$T$2:$T$326,$B39,Detalle!$H$2:$H$326,$B49) | E49: =SUMIFS(Detalle!$M$2:$M$326,Detalle!$T$2:$T$326,$B39,Detalle!$H$2:$H$326,$B49) | F49: =D49+E49
B50: MINIBREAKER MONOPOLAR PARA RIEL 6AMP SIEMENS - UND | C50: =SUMIFS(Detalle!$I$2:$I$326,Detalle!$T$2:$T$326,$B39,Detalle!$H$2:$H$326,$B50) | D50: =SUMIFS(Detalle!$K$2:$K$326,Detalle!$T$2:$T$326,$B39,Detalle!$H$2:$H$326,$B50) | E50: =SUMIFS(Detalle!$M$2:$M$326,Detalle!$T$2:$T$326,$B39,Detalle!$H$2:$H$326,$B50) | F50: =D50+E50
B51: Cerramiento perimetral | C51: =SUMIFS(Detalle!$I$2:$I$326,Detalle!$T$2:$T$326,$B51) | D51: =SUMIFS(Detalle!$K$2:$K$326,Detalle!$T$2:$T$326,$B51) | E51: =SUMIFS(Detalle!$M$2:$M$326,Detalle!$T$2:$T$326,$B51) | F51: =D51+E51
B52: CERRAMIENTO PERIMETRAL - UND | C52: =SUMIFS(Detalle!$I$2:$I$326,Detalle!$T$2:$T$326,$B51,Detalle!$H$2:$H$326,$B52) | D52: =SUMIFS(Detalle!$K$2:$K$326,Detalle!$T$2:$T$326,$B51,Detalle!$H$2:$H$326,$B52) | E52: =SUMIFS(Detalle!$M$2:$M$326,Detalle!$T$2:$T$326,$B51,Detalle!$H$2:$H$326,$B52) | F52: =D52+E52
B53: SUMINISTRO DE PORTON METALICO MEDIDAS DE 2.38 MT x 2.40 MT. EN LAMINA GALVANIZADA CALIBRE 20, EN DOS HOJAS Y CON CHAPA ANTIPANICO. - UND | C53: =SUMIFS(Detalle!$I$2:$I$326,Detalle!$T$2:$T$326,$B51,Detalle!$H$2:$H$326,$B53) | D53: =SUMIFS(Detalle!$K$2:$K$326,Detalle!$T$2:$T$326,$B51,Detalle!$H$2:$H$326,$B53) | E53: =SUMIFS(Detalle!$M$2:$M$326,Detalle!$T$2:$T$326,$B51,Detalle!$H$2:$H$326,$B53) | F53: =D53+E53
B54: SUMINISTRO DE PORTON METALICO DE 2 MT x 2.40 MT EN LAMINA GALVANIZADA CALIBRE 20 EN 2 HOJAS Y CON CHAPA ANTIPANICO. - UND | C54: =SUMIFS(Detalle!$I$2:$I$326,Detalle!$T$2:$T$326,$B51,Detalle!$H$2:$H$326,$B54) | D54: =SUMIFS(Detalle!$K$2:$K$326,Detalle!$T$2:$T$326,$B51,Detalle!$H$2:$H$326,$B54) | E54: =SUMIFS(Detalle!$M$2:$M$326,Detalle!$T$2:$T$326,$B51,Detalle!$H$2:$H$326,$B54) | F54: =D54+E54
B55: Obra civil (concreto, agregados) | C55: =SUMIFS(Detalle!$I$2:$I$326,Detalle!$T$2:$T$326,$B55) | D55: =SUMIFS(Detalle!$K$2:$K$326,Detalle!$T$2:$T$326,$B55) | E55: =SUMIFS(Detalle!$M$2:$M$326,Detalle!$T$2:$T$326,$B55) | F55: =D55+E55
B56: CEMENTO GRIS X BULTO - UND | C56: =SUMIFS(Detalle!$I$2:$I$326,Detalle!$T$2:$T$326,$B55,Detalle!$H$2:$H$326,$B56) | D56: =SUMIFS(Detalle!$K$2:$K$326,Detalle!$T$2:$T$326,$B55,Detalle!$H$2:$H$326,$B56) | E56: =SUMIFS(Detalle!$M$2:$M$326,Detalle!$T$2:$T$326,$B55,Detalle!$H$2:$H$326,$B56) | F56: =D56+E56
B57: CRUDO DE RÍO X M3 - M3 | C57: =SUMIFS(Detalle!$I$2:$I$326,Detalle!$T$2:$T$326,$B55,Detalle!$H$2:$H$326,$B57) | D57: =SUMIFS(Detalle!$K$2:$K$326,Detalle!$T$2:$T$326,$B55,Detalle!$H$2:$H$326,$B57) | E57: =SUMIFS(Detalle!$M$2:$M$326,Detalle!$T$2:$T$326,$B55,Detalle!$H$2:$H$326,$B57) | F57: =D57+E57
B58: TRITURADO 3/4 - M3 | C58: =SUMIFS(Detalle!$I$2:$I$326,Detalle!$T$2:$T$326,$B55,Detalle!$H$2:$H$326,$B58) | D58: =SUMIFS(Detalle!$K$2:$K$326,Detalle!$T$2:$T$326,$B55,Detalle!$H$2:$H$326,$B58) | E58: =SUMIFS(Detalle!$M$2:$M$326,Detalle!$T$2:$T$326,$B55,Detalle!$H$2:$H$326,$B58) | F58: =D58+E58
B59: RECEBO - M3 | C59: =SUMIFS(Detalle!$I$2:$I$326,Detalle!$T$2:$T$326,$B55,Detalle!$H$2:$H$326,$B59) | D59: =SUMIFS(Detalle!$K$2:$K$326,Detalle!$T$2:$T$326,$B55,Detalle!$H$2:$H$326,$B59) | E59: =SUMIFS(Detalle!$M$2:$M$326,Detalle!$T$2:$T$326,$B55,Detalle!$H$2:$H$326,$B59) | F59: =D59+E59
B60: ARENA DE RIO METRO CUBICO - UND | C60: =SUMIFS(Detalle!$I$2:$I$326,Detalle!$T$2:$T$326,$B55,Detalle!$H$2:$H$326,$B60) | D60: =SUMIFS(Detalle!$K$2:$K$326,Detalle!$T$2:$T$326,$B55,Detalle!$H$2:$H$326,$B60) | E60: =SUMIFS(Detalle!$M$2:$M$326,Detalle!$T$2:$T$326,$B55,Detalle!$H$2:$H$326,$B60) | F60: =D60+E60
B61: CEMENTO BLANCO X KG - UND | C61: =SUMIFS(Detalle!$I$2:$I$326,Detalle!$T$2:$T$326,$B55,Detalle!$H$2:$H$326,$B61) | D61: =SUMIFS(Detalle!$K$2:$K$326,Detalle!$T$2:$T$326,$B55,Detalle!$H$2:$H$326,$B61) | E61: =SUMIFS(Detalle!$M$2:$M$326,Detalle!$T$2:$T$326,$B55,Detalle!$H$2:$H$326,$B61) | F61: =D61+E61
B62: TRITURADO FINO METRO CUBICO - UND | C62: =SUMIFS(Detalle!$I$2:$I$326,Detalle!$T$2:$T$326,$B55,Detalle!$H$2:$H$326,$B62) | D62: =SUMIFS(Detalle!$K$2:$K$326,Detalle!$T$2:$T$326,$B55,Detalle!$H$2:$H$326,$B62) | E62: =SUMIFS(Detalle!$M$2:$M$326,Detalle!$T$2:$T$326,$B55,Detalle!$H$2:$H$326,$B62) | F62: =D62+E62
B63: CHIPA DE ACERO 3/8 CORRUGADA - UND | C63: =SUMIFS(Detalle!$I$2:$I$326,Detalle!$T$2:$T$326,$B55,Detalle!$H$2:$H$326,$B63) | D63: =SUMIFS(Detalle!$K$2:$K$326,Detalle!$T$2:$T$326,$B55,Detalle!$H$2:$H$326,$B63) | E63: =SUMIFS(Detalle!$M$2:$M$326,Detalle!$T$2:$T$326,$B55,Detalle!$H$2:$H$326,$B63) | F63: =D63+E63
B64: VARILLA CORRUGADA PARA CONSTRUCCIÓN 1/2" X 6M - UND | C64: =SUMIFS(Detalle!$I$2:$I$326,Detalle!$T$2:$T$326,$B55,Detalle!$H$2:$H$326,$B64) | D64: =SUMIFS(Detalle!$K$2:$K$326,Detalle!$T$2:$T$326,$B55,Detalle!$H$2:$H$326,$B64) | E64: =SUMIFS(Detalle!$M$2:$M$326,Detalle!$T$2:$T$326,$B55,Detalle!$H$2:$H$326,$B64) | F64: =D64+E64
B65: LADRILLO COMUN 9.5 X 11 X 21 CM - UND | C65: =SUMIFS(Detalle!$I$2:$I$326,Detalle!$T$2:$T$326,$B55,Detalle!$H$2:$H$326,$B65) | D65: =SUMIFS(Detalle!$K$2:$K$326,Detalle!$T$2:$T$326,$B55,Detalle!$H$2:$H$326,$B65) | E65: =SUMIFS(Detalle!$M$2:$M$326,Detalle!$T$2:$T$326,$B55,Detalle!$H$2:$H$326,$B65) | F65: =D65+E65
B66: ARENA X M3 - UND | C66: =SUMIFS(Detalle!$I$2:$I$326,Detalle!$T$2:$T$326,$B55,Detalle!$H$2:$H$326,$B66) | D66: =SUMIFS(Detalle!$K$2:$K$326,Detalle!$T$2:$T$326,$B55,Detalle!$H$2:$H$326,$B66) | E66: =SUMIFS(Detalle!$M$2:$M$326,Detalle!$T$2:$T$326,$B55,Detalle!$H$2:$H$326,$B66) | F66: =D66+E66
B67: VARILLA CORRUGADA PARA CONSTRUCCIÓN 3/8" X 6M - UND | C67: =SUMIFS(Detalle!$I$2:$I$326,Detalle!$T$2:$T$326,$B55,Detalle!$H$2:$H$326,$B67) | D67: =SUMIFS(Detalle!$K$2:$K$326,Detalle!$T$2:$T$326,$B55,Detalle!$H$2:$H$326,$B67) | E67: =SUMIFS(Detalle!$M$2:$M$326,Detalle!$T$2:$T$326,$B55,Detalle!$H$2:$H$326,$B67) | F67: =D67+E67
B68: TABLA ORDINARIA - UND | C68: =SUMIFS(Detalle!$I$2:$I$326,Detalle!$T$2:$T$326,$B55,Detalle!$H$2:$H$326,$B68) | D68: =SUMIFS(Detalle!$K$2:$K$326,Detalle!$T$2:$T$326,$B55,Detalle!$H$2:$H$326,$B68) | E68: =SUMIFS(Detalle!$M$2:$M$326,Detalle!$T$2:$T$326,$B55,Detalle!$H$2:$H$326,$B68) | F68: =D68+E68
B69: MALLA ELECTROSOLDADA 6MM - UND | C69: =SUMIFS(Detalle!$I$2:$I$326,Detalle!$T$2:$T$326,$B55,Detalle!$H$2:$H$326,$B69) | D69: =SUMIFS(Detalle!$K$2:$K$326,Detalle!$T$2:$T$326,$B55,Detalle!$H$2:$H$326,$B69) | E69: =SUMIFS(Detalle!$M$2:$M$326,Detalle!$T$2:$T$326,$B55,Detalle!$H$2:$H$326,$B69) | F69: =D69+E69
B70: SUB BASE GRANULAR X M3 - M3 | C70: =SUMIFS(Detalle!$I$2:$I$326,Detalle!$T$2:$T$326,$B55,Detalle!$H$2:$H$326,$B70) | D70: =SUMIFS(Detalle!$K$2:$K$326,Detalle!$T$2:$T$326,$B55,Detalle!$H$2:$H$326,$B70) | E70: =SUMIFS(Detalle!$M$2:$M$326,Detalle!$T$2:$T$326,$B55,Detalle!$H$2:$H$326,$B70) | F70: =D70+E70
B71: ARENA DE TRITURACIÓN - M3 | C71: =SUMIFS(Detalle!$I$2:$I$326,Detalle!$T$2:$T$326,$B55,Detalle!$H$2:$H$326,$B71) | D71: =SUMIFS(Detalle!$K$2:$K$326,Detalle!$T$2:$T$326,$B55,Detalle!$H$2:$H$326,$B71) | E71: =SUMIFS(Detalle!$M$2:$M$326,Detalle!$T$2:$T$326,$B55,Detalle!$H$2:$H$326,$B71) | F71: =D71+E71
B72: CHIPA DE ACERO 1/4 CORRUGADA - KILO | C72: =SUMIFS(Detalle!$I$2:$I$326,Detalle!$T$2:$T$326,$B55,Detalle!$H$2:$H$326,$B72) | D72: =SUMIFS(Detalle!$K$2:$K$326,Detalle!$T$2:$T$326,$B55,Detalle!$H$2:$H$326,$B72) | E72: =SUMIFS(Detalle!$M$2:$M$326,Detalle!$T$2:$T$326,$B55,Detalle!$H$2:$H$326,$B72) | F72: =D72+E72
B73: DISCO PARA CORTE DE CONCRETO EN EJE 7/8" (DIAMETRO 7") - UND | C73: =SUMIFS(Detalle!$I$2:$I$326,Detalle!$T$2:$T$326,$B55,Detalle!$H$2:$H$326,$B73) | D73: =SUMIFS(Detalle!$K$2:$K$326,Detalle!$T$2:$T$326,$B55,Detalle!$H$2:$H$326,$B73) | E73: =SUMIFS(Detalle!$M$2:$M$326,Detalle!$T$2:$T$326,$B55,Detalle!$H$2:$H$326,$B73) | F73: =D73+E73
B74: Inversores | C74: =SUMIFS(Detalle!$I$2:$I$326,Detalle!$T$2:$T$326,$B74) | D74: =SUMIFS(Detalle!$K$2:$K$326,Detalle!$T$2:$T$326,$B74) | E74: =SUMIFS(Detalle!$M$2:$M$326,Detalle!$T$2:$T$326,$B74) | F74: =D74+E74
B75: HUAWEI SIN2000 - 330 KTL - H1 (INVERSOR) - UND | C75: =SUMIFS(Detalle!$I$2:$I$326,Detalle!$T$2:$T$326,$B74,Detalle!$H$2:$H$326,$B75) | D75: =SUMIFS(Detalle!$K$2:$K$326,Detalle!$T$2:$T$326,$B74,Detalle!$H$2:$H$326,$B75) | E75: =SUMIFS(Detalle!$M$2:$M$326,Detalle!$T$2:$T$326,$B74,Detalle!$H$2:$H$326,$B75) | F75: =D75+E75
B76: HUAWEI SUN2000 - 50 KTL - M3 (INVERSOR) - UND | C76: =SUMIFS(Detalle!$I$2:$I$326,Detalle!$T$2:$T$326,$B74,Detalle!$H$2:$H$326,$B76) | D76: =SUMIFS(Detalle!$K$2:$K$326,Detalle!$T$2:$T$326,$B74,Detalle!$H$2:$H$326,$B76) | E76: =SUMIFS(Detalle!$M$2:$M$326,Detalle!$T$2:$T$326,$B74,Detalle!$H$2:$H$326,$B76) | F76: =D76+E76
B77: HUAWEI SUN2000 - 40 KTL - M3 (INVERSOR) - UND | C77: =SUMIFS(Detalle!$I$2:$I$326,Detalle!$T$2:$T$326,$B74,Detalle!$H$2:$H$326,$B77) | D77: =SUMIFS(Detalle!$K$2:$K$326,Detalle!$T$2:$T$326,$B74,Detalle!$H$2:$H$326,$B77) | E77: =SUMIFS(Detalle!$M$2:$M$326,Detalle!$T$2:$T$326,$B74,Detalle!$H$2:$H$326,$B77) | F77: =D77+E77
B78: SUMINISTRO DE SOPORTES INVERSORES EXTERNOS EN TUBO DE 100X100-1.5MM - UND | C78: =SUMIFS(Detalle!$I$2:$I$326,Detalle!$T$2:$T$326,$B74,Detalle!$H$2:$H$326,$B78) | D78: =SUMIFS(Detalle!$K$2:$K$326,Detalle!$T$2:$T$326,$B74,Detalle!$H$2:$H$326,$B78) | E78: =SUMIFS(Detalle!$M$2:$M$326,Detalle!$T$2:$T$326,$B74,Detalle!$H$2:$H$326,$B78) | F78: =D78+E78
B79: SUMINISTRO DE SOPORTES INVERSORES INTERNOS EN TUBO DE 3X1 1/2" CAL. 16 - UND | C79: =SUMIFS(Detalle!$I$2:$I$326,Detalle!$T$2:$T$326,$B74,Detalle!$H$2:$H$326,$B79) | D79: =SUMIFS(Detalle!$K$2:$K$326,Detalle!$T$2:$T$326,$B74,Detalle!$H$2:$H$326,$B79) | E79: =SUMIFS(Detalle!$M$2:$M$326,Detalle!$T$2:$T$326,$B74,Detalle!$H$2:$H$326,$B79) | F79: =D79+E79
B80: SUMINISTRO DE PLATINAS BASE PARA SOPORTES DE INVERSORES EXTERIORES DE 0.15X0.15 MTS CAL. 1/4" - UND | C80: =SUMIFS(Detalle!$I$2:$I$326,Detalle!$T$2:$T$326,$B74,Detalle!$H$2:$H$326,$B80) | D80: =SUMIFS(Detalle!$K$2:$K$326,Detalle!$T$2:$T$326,$B74,Detalle!$H$2:$H$326,$B80) | E80: =SUMIFS(Detalle!$M$2:$M$326,Detalle!$T$2:$T$326,$B74,Detalle!$H$2:$H$326,$B80) | F80: =D80+E80
B81: Cableado y conductores | C81: =SUMIFS(Detalle!$I$2:$I$326,Detalle!$T$2:$T$326,$B81) | D81: =SUMIFS(Detalle!$K$2:$K$326,Detalle!$T$2:$T$326,$B81) | E81: =SUMIFS(Detalle!$M$2:$M$326,Detalle!$T$2:$T$326,$B81) | F81: =D81+E81
B82: CABLE SOLAR 4mm NEGRO (PROCABLES) 1014-31399000601C - UND | C82: =SUMIFS(Detalle!$I$2:$I$326,Detalle!$T$2:$T$326,$B81,Detalle!$H$2:$H$326,$B82) | D82: =SUMIFS(Detalle!$K$2:$K$326,Detalle!$T$2:$T$326,$B81,Detalle!$H$2:$H$326,$B82) | E82: =SUMIFS(Detalle!$M$2:$M$326,Detalle!$T$2:$T$326,$B81,Detalle!$H$2:$H$326,$B82) | F82: =D82+E82
B83: CABLE CU 500KCMIL CENTELFLEX (253mm²) 6/1kV - UND | C83: =SUMIFS(Detalle!$I$2:$I$326,Detalle!$T$2:$T$326,$B81,Detalle!$H$2:$H$326,$B83) | D83: =SUMIFS(Detalle!$K$2:$K$326,Detalle!$T$2:$T$326,$B81,Detalle!$H$2:$H$326,$B83) | E83: =SUMIFS(Detalle!$M$2:$M$326,Detalle!$T$2:$T$326,$B81,Detalle!$H$2:$H$326,$B83) | F83: =D83+E83
B84: CABLE CU DESNUDO 1/0 AWG 19H - UND | C84: =SUMIFS(Detalle!$I$2:$I$326,Detalle!$T$2:$T$326,$B81,Detalle!$H$2:$H$326,$B84) | D84: =SUMIFS(Detalle!$K$2:$K$326,Detalle!$T$2:$T$326,$B81,Detalle!$H$2:$H$326,$B84) | E84: =SUMIFS(Detalle!$M$2:$M$326,Detalle!$T$2:$T$326,$B81,Detalle!$H$2:$H$326,$B84) | F84: =D84+E84
B85: CABLE CU 1/0 AWG X METRO - UND | C85: =SUMIFS(Detalle!$I$2:$I$326,Detalle!$T$2:$T$326,$B81,Detalle!$H$2:$H$326,$B85) | D85: =SUMIFS(Detalle!$K$2:$K$326,Detalle!$T$2:$T$326,$B81,Detalle!$H$2:$H$326,$B85) | E85: =SUMIFS(Detalle!$M$2:$M$326,Detalle!$T$2:$T$326,$B81,Detalle!$H$2:$H$326,$B85) | F85: =D85+E85
B86: CABLE SIETE HILOS CU 6 NEGRO X METRO - UND | C86: =SUMIFS(Detalle!$I$2:$I$326,Detalle!$T$2:$T$326,$B81,Detalle!$H$2:$H$326,$B86) | D86: =SUMIFS(Detalle!$K$2:$K$326,Detalle!$T$2:$T$326,$B81,Detalle!$H$2:$H$326,$B86) | E86: =SUMIFS(Detalle!$M$2:$M$326,Detalle!$T$2:$T$326,$B81,Detalle!$H$2:$H$326,$B86) | F86: =D86+E86
B87: BORNA 500 MCM TERMINAL BIMETALICA - CILES - UND | C87: =SUMIFS(Detalle!$I$2:$I$326,Detalle!$T$2:$T$326,$B81,Detalle!$H$2:$H$326,$B87) | D87: =SUMIFS(Detalle!$K$2:$K$326,Detalle!$T$2:$T$326,$B81,Detalle!$H$2:$H$326,$B87) | E87: =SUMIFS(Detalle!$M$2:$M$326,Detalle!$T$2:$T$326,$B81,Detalle!$H$2:$H$326,$B87) | F87: =D87+E87
B88: CABLE AL 1/0 X METRO - UND | C88: =SUMIFS(Detalle!$I$2:$I$326,Detalle!$T$2:$T$326,$B81,Detalle!$H$2:$H$326,$B88) | D88: =SUMIFS(Detalle!$K$2:$K$326,Detalle!$T$2:$T$326,$B81,Detalle!$H$2:$H$326,$B88) | E88: =SUMIFS(Detalle!$M$2:$M$326,Detalle!$T$2:$T$326,$B81,Detalle!$H$2:$H$326,$B88) | F88: =D88+E88
B89: TERMINAL PREMOLDEADO 15KV INTERIOR 3-3/0 REF 5623K QTII (PRO 2-4/0) (CEN 2-3/0)3M - UND | C89: =SUMIFS(Detalle!$I$2:$I$326,Detalle!$T$2:$T$326,$B81,Detalle!$H$2:$H$326,$B89) | D89: =SUMIFS(Detalle!$K$2:$K$326,Detalle!$T$2:$T$326,$B81,Detalle!$H$2:$H$326,$B89) | E89: =SUMIFS(Detalle!$M$2:$M$326,Detalle!$T$2:$T$326,$B81,Detalle!$H$2:$H$326,$B89) | F89: =D89+E89
B90: TERMINAL PREMOLDEADO 15KV EXTERIOR 2-4/0 REF 5633K QTII (PRO 2-4/0) (CEN 2-4/0) 3M - UND | C90: =SUMIFS(Detalle!$I$2:$I$326,Detalle!$T$2:$T$326,$B81,Detalle!$H$2:$H$326,$B90) | D90: =SUMIFS(Detalle!$K$2:$K$326,Detalle!$T$2:$T$326,$B81,Detalle!$H$2:$H$326,$B90) | E90: =SUMIFS(Detalle!$M$2:$M$326,Detalle!$T$2:$T$326,$B81,Detalle!$H$2:$H$326,$B90) | F90: =D90+E90
B91: BORNA 500 MCM TERMINAL 1/H 31067 3M - UND | C91: =SUMIFS(Detalle!$I$2:$I$326,Detalle!$T$2:$T$326,$B81,Detalle!$H$2:$H$326,$B91) | D91: =SUMIFS(Detalle!$K$2:$K$326,Detalle!$T$2:$T$326,$B81,Detalle!$H$2:$H$326,$B91) | E91: =SUMIFS(Detalle!$M$2:$M$326,Detalle!$T$2:$T$326,$B81,Detalle!$H$2:$H$326,$B91) | F91: =D91+E91
B92: CONECTOR MC4 EN JUEGO - UND | C92: =SUMIFS(Detalle!$I$2:$I$326,Detalle!$T$2:$T$326,$B81,Detalle!$H$2:$H$326,$B92) | D92: =SUMIFS(Detalle!$K$2:$K$326,Detalle!$T$2:$T$326,$B81,Detalle!$H$2:$H$326,$B92) | E92: =SUMIFS(Detalle!$M$2:$M$326,Detalle!$T$2:$T$326,$B81,Detalle!$H$2:$H$326,$B92) | F92: =D92+E92
B93: BANDEJA PORTACABLE TIPO ESCALERA SEMIPESADA 15 BARROTES 50 X 8 X 24 MT GALV/CALIENTE - GALCO - UND | C93: =SUMIFS(Detalle!$I$2:$I$326,Detalle!$T$2:$T$326,$B81,Detalle!$H$2:$H$326,$B93) | D93: =SUMIFS(Detalle!$K$2:$K$326,Detalle!$T$2:$T$326,$B81,Detalle!$H$2:$H$326,$B93) | E93: =SUMIFS(Detalle!$M$2:$M$326,Detalle!$T$2:$T$326,$B81,Detalle!$H$2:$H$326,$B93) | F93: =D93+E93
B94: CABLE CU 12 NEGRO THHN/THWN AISLA NYLON (PROCABLES-BOBINA) 1002- 3135308100-001B - UND | C94: =SUMIFS(Detalle!$I$2:$I$326,Detalle!$T$2:$T$326,$B81,Detalle!$H$2:$H$326,$B94) | D94: =SUMIFS(Detalle!$K$2:$K$326,Detalle!$T$2:$T$326,$B81,Detalle!$H$2:$H$326,$B94) | E94: =SUMIFS(Detalle!$M$2:$M$326,Detalle!$T$2:$T$326,$B81,Detalle!$H$2:$H$326,$B94) | F94: =D94+E94
B95: ALAMBRE DE AMARRE X KG - UND | C95: =SUMIFS(Detalle!$I$2:$I$326,Detalle!$T$2:$T$326,$B81,Detalle!$H$2:$H$326,$B95) | D95: =SUMIFS(Detalle!$K$2:$K$326,Detalle!$T$2:$T$326,$B81,Detalle!$H$2:$H$326,$B95) | E95: =SUMIFS(Detalle!$M$2:$M$326,Detalle!$T$2:$T$326,$B81,Detalle!$H$2:$H$326,$B95) | F95: =D95+E95
B96: CONECTOR RECTO DE CORAZA 3" - UND | C96: =SUMIFS(Detalle!$I$2:$I$326,Detalle!$T$2:$T$326,$B81,Detalle!$H$2:$H$326,$B96) | D96: =SUMIFS(Detalle!$K$2:$K$326,Detalle!$T$2:$T$326,$B81,Detalle!$H$2:$H$326,$B96) | E96: =SUMIFS(Detalle!$M$2:$M$326,Detalle!$T$2:$T$326,$B81,Detalle!$H$2:$H$326,$B96) | F96: =D96+E96
B97: BANDEJA PORTACABLE TIPO ESCALERA 20X8X2.401305-CM GALVANIZADA - UND | C97: =SUMIFS(Detalle!$I$2:$I$326,Detalle!$T$2:$T$326,$B81,Detalle!$H$2:$H$326,$B97) | D97: =SUMIFS(Detalle!$K$2:$K$326,Detalle!$T$2:$T$326,$B81,Detalle!$H$2:$H$326,$B97) | E97: =SUMIFS(Detalle!$M$2:$M$326,Detalle!$T$2:$T$326,$B81,Detalle!$H$2:$H$326,$B97) | F97: =D97+E97
B98: CORAZA AMERICANA 2" - UND | C98: =SUMIFS(Detalle!$I$2:$I$326,Detalle!$T$2:$T$326,$B81,Detalle!$H$2:$H$326,$B98) | D98: =SUMIFS(Detalle!$K$2:$K$326,Detalle!$T$2:$T$326,$B81,Detalle!$H$2:$H$326,$B98) | E98: =SUMIFS(Detalle!$M$2:$M$326,Detalle!$T$2:$T$326,$B81,Detalle!$H$2:$H$326,$B98) | F98: =D98+E98
B99: MARCADOR P/MULTICONDUCTORES 500 DEXSON 2103-DXN2601I - UND | C99: =SUMIFS(Detalle!$I$2:$I$326,Detalle!$T$2:$T$326,$B81,Detalle!$H$2:$H$326,$B99) | D99: =SUMIFS(Detalle!$K$2:$K$326,Detalle!$T$2:$T$326,$B81,Detalle!$H$2:$H$326,$B99) | E99: =SUMIFS(Detalle!$M$2:$M$326,Detalle!$T$2:$T$326,$B81,Detalle!$H$2:$H$326,$B99) | F99: =D99+E99
B100: MOLDE EN T 1/0-1/0 CABLE - CABLE - GROUNDING - UND | C100: =SUMIFS(Detalle!$I$2:$I$326,Detalle!$T$2:$T$326,$B81,Detalle!$H$2:$H$326,$B100) | D100: =SUMIFS(Detalle!$K$2:$K$326,Detalle!$T$2:$T$326,$B81,Detalle!$H$2:$H$326,$B100) | E100: =SUMIFS(Detalle!$M$2:$M$326,Detalle!$T$2:$T$326,$B81,Detalle!$H$2:$H$326,$B100) | F100: =D100+E100
B101: CABLE AL 2 AWG X METRO - UND | C101: =SUMIFS(Detalle!$I$2:$I$326,Detalle!$T$2:$T$326,$B81,Detalle!$H$2:$H$326,$B101) | D101: =SUMIFS(Detalle!$K$2:$K$326,Detalle!$T$2:$T$326,$B81,Detalle!$H$2:$H$326,$B101) | E101: =SUMIFS(Detalle!$M$2:$M$326,Detalle!$T$2:$T$326,$B81,Detalle!$H$2:$H$326,$B101) | F101: =D101+E101
B102: CABLE UTP CAT 6 INTERIOR LSZH GRIS X 1000 MTS EVSOLUTIONS - UND | C102: =SUMIFS(Detalle!$I$2:$I$326,Detalle!$T$2:$T$326,$B81,Detalle!$H$2:$H$326,$B102) | D102: =SUMIFS(Detalle!$K$2:$K$326,Detalle!$T$2:$T$326,$B81,Detalle!$H$2:$H$326,$B102) | E102: =SUMIFS(Detalle!$M$2:$M$326,Detalle!$T$2:$T$326,$B81,Detalle!$H$2:$H$326,$B102) | F102: =D102+E102
B103: CONECTOR RECTO DE CORAZA 2" - UND | C103: =SUMIFS(Detalle!$I$2:$I$326,Detalle!$T$2:$T$326,$B81,Detalle!$H$2:$H$326,$B103) | D103: =SUMIFS(Detalle!$K$2:$K$326,Detalle!$T$2:$T$326,$B81,Detalle!$H$2:$H$326,$B103) | E103: =SUMIFS(Detalle!$M$2:$M$326,Detalle!$T$2:$T$326,$B81,Detalle!$H$2:$H$326,$B103) | F103: =D103+E103
B104: CABLE VEHICULAR CU 16 NEGRO X METRO - UND | C104: =SUMIFS(Detalle!$I$2:$I$326,Detalle!$T$2:$T$326,$B81,Detalle!$H$2:$H$326,$B104) | D104: =SUMIFS(Detalle!$K$2:$K$326,Detalle!$T$2:$T$326,$B81,Detalle!$H$2:$H$326,$B104) | E104: =SUMIFS(Detalle!$M$2:$M$326,Detalle!$T$2:$T$326,$B81,Detalle!$H$2:$H$326,$B104) | F104: =D104+E104
B105: BORNA 6 AWG TERMINAL 1/H T/AMERICANO - UND | C105: =SUMIFS(Detalle!$I$2:$I$326,Detalle!$T$2:$T$326,$B81,Detalle!$H$2:$H$326,$B105) | D105: =SUMIFS(Detalle!$K$2:$K$326,Detalle!$T$2:$T$326,$B81,Detalle!$H$2:$H$326,$B105) | E105: =SUMIFS(Detalle!$M$2:$M$326,Detalle!$T$2:$T$326,$B81,Detalle!$H$2:$H$326,$B105) | F105: =D105+E105
B106: UNION BANDEJA PORTACABLE GALVANIZADA - UND | C106: =SUMIFS(Detalle!$I$2:$I$326,Detalle!$T$2:$T$326,$B81,Detalle!$H$2:$H$326,$B106) | D106: =SUMIFS(Detalle!$K$2:$K$326,Detalle!$T$2:$T$326,$B81,Detalle!$H$2:$H$326,$B106) | E106: =SUMIFS(Detalle!$M$2:$M$326,Detalle!$T$2:$T$326,$B81,Detalle!$H$2:$H$326,$B106) | F106: =D106+E106
B107: CONECTOR BIMETALUCO 1 PERNO 6-2-0 1021B - UND | C107: =SUMIFS(Detalle!$I$2:$I$326,Detalle!$T$2:$T$326,$B81,Detalle!$H$2:$H$326,$B107) | D107: =SUMIFS(Detalle!$K$2:$K$326,Detalle!$T$2:$T$326,$B81,Detalle!$H$2:$H$326,$B107) | E107: =SUMIFS(Detalle!$M$2:$M$326,Detalle!$T$2:$T$326,$B81,Detalle!$H$2:$H$326,$B107) | F107: =D107+E107
B108: BORNA 1/0 TERMINAL BIMETALICA - CILES - UND | C108: =SUMIFS(Detalle!$I$2:$I$326,Detalle!$T$2:$T$326,$B81,Detalle!$H$2:$H$326,$B108) | D108: =SUMIFS(Detalle!$K$2:$K$326,Detalle!$T$2:$T$326,$B81,Detalle!$H$2:$H$326,$B108) | E108: =SUMIFS(Detalle!$M$2:$M$326,Detalle!$T$2:$T$326,$B81,Detalle!$H$2:$H$326,$B108) | F108: =D108+E108
B109: BORNERA 2 AWG BIMETÁLICA CILES PALA ANGOSTA - UND | C109: =SUMIFS(Detalle!$I$2:$I$326,Detalle!$T$2:$T$326,$B81,Detalle!$H$2:$H$326,$B109) | D109: =SUMIFS(Detalle!$K$2:$K$326,Detalle!$T$2:$T$326,$B81,Detalle!$H$2:$H$326,$B109) | E109: =SUMIFS(Detalle!$M$2:$M$326,Detalle!$T$2:$T$326,$B81,Detalle!$H$2:$H$326,$B109) | F109: =D109+E109
B110: BORNA 1/0 AWG TERMINAL 1/H T/AMERICANO - UND | C110: =SUMIFS(Detalle!$I$2:$I$326,Detalle!$T$2:$T$326,$B81,Detalle!$H$2:$H$326,$B110) | D110: =SUMIFS(Detalle!$K$2:$K$326,Detalle!$T$2:$T$326,$B81,Detalle!$H$2:$H$326,$B110) | E110: =SUMIFS(Detalle!$M$2:$M$326,Detalle!$T$2:$T$326,$B81,Detalle!$H$2:$H$326,$B110) | F110: =D110+E110
B111: CABLE CU ENCAUCHETADO 3X12 AWG 600V - UND | C111: =SUMIFS(Detalle!$I$2:$I$326,Detalle!$T$2:$T$326,$B81,Detalle!$H$2:$H$326,$B111) | D111: =SUMIFS(Detalle!$K$2:$K$326,Detalle!$T$2:$T$326,$B81,Detalle!$H$2:$H$326,$B111) | E111: =SUMIFS(Detalle!$M$2:$M$326,Detalle!$T$2:$T$326,$B81,Detalle!$H$2:$H$326,$B111) | F111: =D111+E111
B112: BORNA 2 AWG TERMINAL BIMETALICA - CILES - UND | C112: =SUMIFS(Detalle!$I$2:$I$326,Detalle!$T$2:$T$326,$B81,Detalle!$H$2:$H$326,$B112) | D112: =SUMIFS(Detalle!$K$2:$K$326,Detalle!$T$2:$T$326,$B81,Detalle!$H$2:$H$326,$B112) | E112: =SUMIFS(Detalle!$M$2:$M$326,Detalle!$T$2:$T$326,$B81,Detalle!$H$2:$H$326,$B112) | F112: =D112+E112
B113: CORAZA AMERICANA 3/4" METRO - METRO | C113: =SUMIFS(Detalle!$I$2:$I$326,Detalle!$T$2:$T$326,$B81,Detalle!$H$2:$H$326,$B113) | D113: =SUMIFS(Detalle!$K$2:$K$326,Detalle!$T$2:$T$326,$B81,Detalle!$H$2:$H$326,$B113) | E113: =SUMIFS(Detalle!$M$2:$M$326,Detalle!$T$2:$T$326,$B81,Detalle!$H$2:$H$326,$B113) | F113: =D113+E113
B114: TERMINAL TIPO FERRUL 10 AWG - UND | C114: =SUMIFS(Detalle!$I$2:$I$326,Detalle!$T$2:$T$326,$B81,Detalle!$H$2:$H$326,$B114) | D114: =SUMIFS(Detalle!$K$2:$K$326,Detalle!$T$2:$T$326,$B81,Detalle!$H$2:$H$326,$B114) | E114: =SUMIFS(Detalle!$M$2:$M$326,Detalle!$T$2:$T$326,$B81,Detalle!$H$2:$H$326,$B114) | F114: =D114+E114
B115: CONECTOR RECTO DE CORAZA 3/4" - UND | C115: =SUMIFS(Detalle!$I$2:$I$326,Detalle!$T$2:$T$326,$B81,Detalle!$H$2:$H$326,$B115) | D115: =SUMIFS(Detalle!$K$2:$K$326,Detalle!$T$2:$T$326,$B81,Detalle!$H$2:$H$326,$B115) | E115: =SUMIFS(Detalle!$M$2:$M$326,Detalle!$T$2:$T$326,$B81,Detalle!$H$2:$H$326,$B115) | F115: =D115+E115
B116: TERMINAL ANILLO AMARILLO 12-10 AWG 1/4 - UND | C116: =SUMIFS(Detalle!$I$2:$I$326,Detalle!$T$2:$T$326,$B81,Detalle!$H$2:$H$326,$B116) | D116: =SUMIFS(Detalle!$K$2:$K$326,Detalle!$T$2:$T$326,$B81,Detalle!$H$2:$H$326,$B116) | E116: =SUMIFS(Detalle!$M$2:$M$326,Detalle!$T$2:$T$326,$B81,Detalle!$H$2:$H$326,$B116) | F116: =D116+E116
B117: Servicios de obra e ingeniería | C117: =SUMIFS(Detalle!$I$2:$I$326,Detalle!$T$2:$T$326,$B117) | D117: =SUMIFS(Detalle!$K$2:$K$326,Detalle!$T$2:$T$326,$B117) | E117: =SUMIFS(Detalle!$M$2:$M$326,Detalle!$T$2:$T$326,$B117) | F117: =D117+E117
...

Sheet Por proveedor
B2: GASTO POR PROVEEDOR
B3: Valores calculados con SUMAR.SI.CONJUNTO sobre la hoja Detalle.
B5: Proveedor | C5: Valor sin IVA | D5: IVA | E5: Total con IVA | F5: % del total
B6: ALURACK S.A.S. | C6: =SUMIFS(Detalle!$K$2:$K$326,Detalle!$P$2:$P$326,$B6) | D6: =SUMIFS(Detalle!$M$2:$M$326,Detalle!$P$2:$P$326,$B6) | E6: =C6+D6 | F6: =IF(SUM(Detalle!$K$2:$K$326)=0,0,C6/SUM(Detalle!$K$2:$K$326))
B7: INGENIERIA Y SOLUCIONES DE NARIÑO SAS | C7: =SUMIFS(Detalle!$K$2:$K$326,Detalle!$P$2:$P$326,$B7) | D7: =SUMIFS(Detalle!$M$2:$M$326,Detalle!$P$2:$P$326,$B7) | E7: =C7+D7 | F7: =IF(SUM(Detalle!$K$2:$K$326)=0,0,C7/SUM(Detalle!$K$2:$K$326))
B8: ELECTRICOS DEL VALLE SAS | C8: =SUMIFS(Detalle!$K$2:$K$326,Detalle!$P$2:$P$326,$B8) | D8: =SUMIFS(Detalle!$M$2:$M$326,Detalle!$P$2:$P$326,$B8) | E8: =C8+D8 | F8: =IF(SUM(Detalle!$K$2:$K$326)=0,0,C8/SUM(Detalle!$K$2:$K$326))
B9: GRUPO SOLAIRE SAS | C9: =SUMIFS(Detalle!$K$2:$K$326,Detalle!$P$2:$P$326,$B9) | D9: =SUMIFS(Detalle!$M$2:$M$326,Detalle!$P$2:$P$326,$B9) | E9: =C9+D9 | F9: =IF(SUM(Detalle!$K$2:$K$326)=0,0,C9/SUM(Detalle!$K$2:$K$326))
B10: CAMPO HELMER PORTILLO PORTILLA | C10: =SUMIFS(Detalle!$K$2:$K$326,Detalle!$P$2:$P$326,$B10) | D10: =SUMIFS(Detalle!$M$2:$M$326,Detalle!$P$2:$P$326,$B10) | E10: =C10+D10 | F10: =IF(SUM(Detalle!$K$2:$K$326)=0,0,C10/SUM(Detalle!$K$2:$K$326))
B11: FAINCO SAS | C11: =SUMIFS(Detalle!$K$2:$K$326,Detalle!$P$2:$P$326,$B11) | D11: =SUMIFS(Detalle!$M$2:$M$326,Detalle!$P$2:$P$326,$B11) | E11: =C11+D11 | F11: =IF(SUM(Detalle!$K$2:$K$326)=0,0,C11/SUM(Detalle!$K$2:$K$326))
B12: HUMBERTO JAVIER ROSERO POTOSI | C12: =SUMIFS(Detalle!$K$2:$K$326,Detalle!$P$2:$P$326,$B12) | D12: =SUMIFS(Detalle!$M$2:$M$326,Detalle!$P$2:$P$326,$B12) | E12: =C12+D12 | F12: =IF(SUM(Detalle!$K$2:$K$326)=0,0,C12/SUM(Detalle!$K$2:$K$326))
B13: MAYERLINE TOBAR GOMEZ | C13: =SUMIFS(Detalle!$K$2:$K$326,Detalle!$P$2:$P$326,$B13) | D13: =SUMIFS(Detalle!$M$2:$M$326,Detalle!$P$2:$P$326,$B13) | E13: =C13+D13 | F13: =IF(SUM(Detalle!$K$2:$K$326)=0,0,C13/SUM(Detalle!$K$2:$K$326))
B14: ANDREA PATRICIA LASSO (FERROPAISA) | C14: =SUMIFS(Detalle!$K$2:$K$326,Detalle!$P$2:$P$326,$B14) | D14: =SUMIFS(Detalle!$M$2:$M$326,Detalle!$P$2:$P$326,$B14) | E14: =C14+D14 | F14: =IF(SUM(Detalle!$K$2:$K$326)=0,0,C14/SUM(Detalle!$K$2:$K$326))
B15: JASSON ALBEIRO VALENCIA ROSERO | C15: =SUMIFS(Detalle!$K$2:$K$326,Detalle!$P$2:$P$326,$B15) | D15: =SUMIFS(Detalle!$M$2:$M$326,Detalle!$P$2:$P$326,$B15) | E15: =C15+D15 | F15: =IF(SUM(Detalle!$K$2:$K$326)=0,0,C15/SUM(Detalle!$K$2:$K$326))
B16: DILIANA HINOJOSA INFANTE (DISTRIBUIDORA DE MATERIALES DYD) | C16: =SUMIFS(Detalle!$K$2:$K$326,Detalle!$P$2:$P$326,$B16) | D16: =SUMIFS(Detalle!$M$2:$M$326,Detalle!$P$2:$P$326,$B16) | E16: =C16+D16 | F16: =IF(SUM(Detalle!$K$2:$K$326)=0,0,C16/SUM(Detalle!$K$2:$K$326))
B17: DAGELEC LTDA | C17: =SUMIFS(Detalle!$K$2:$K$326,Detalle!$P$2:$P$326,$B17) | D17: =SUMIFS(Detalle!$M$2:$M$326,Detalle!$P$2:$P$326,$B17) | E17: =C17+D17 | F17: =IF(SUM(Detalle!$K$2:$K$326)=0,0,C17/SUM(Detalle!$K$2:$K$326))
... B38: SEGURIDAD DEL SUR LIMITADA | C38: =SUMIFS(Detalle!$K$2:$K$326,Detalle!$P$2:$P$326,$B38) | D38: =SUMIFS(Detalle!$M$2:$M$326,Detalle!$P$2:$P$326,$B38) | E38: =C38+D38 | F38: =IF(SUM(Detalle!$K$2:$K$326)=0,0,C38/SUM(Detalle!$K$2:$K$326))
B39: TOTAL | C39: =SUM(Detalle!$K$2:$K$326) | D39: =SUM(Detalle!$M$2:$M$326) | E39: =C39+D39 | F39: 1

Sheet Por estado
B2: COMPRAS POR ESTADO Y LEGALIZACIÓN
B4: Por estado de la orden | E4: Por estado de legalización
B5: Concepto | C5: Valor sin IVA | E5: Concepto | F5: Valor sin IVA
B6: CERRADA | C6: =SUMIFS(Detalle!$K$2:$K$326,Detalle!$D$2:$D$326,B6) | E6: PAGADA | F6: =SUMIFS(Detalle!$K$2:$K$326,Detalle!$E$2:$E$326,E6)
B7: GENERADA | C7: =SUMIFS(Detalle!$K$2:$K$326,Detalle!$D$2:$D$326,B7) | E7: CAUSADA | F7: =SUMIFS(Detalle!$K$2:$K$326,Detalle!$E$2:$E$326,E7)
B8: TOTAL | C8: =SUM(C6:C7) | E8: PENDIENTE | F8: =SUMIFS(Detalle!$K$2:$K$326,Detalle!$E$2:$E$326,E8)
E9: TOTAL | F9: =SUM(F6:F8)
B12: Por tipo de solicitud
B13: Concepto | C13: Valor sin IVA
B14: PLANEADA | C14: =SUMIFS(Detalle!$K$2:$K$326,Detalle!$Q$2:$Q$326,B14)
B15: URGENCIA | C15: =SUMIFS(Detalle!$K$2:$K$326,Detalle!$Q$2:$Q$326,B15)
B16: EMERGENCIA | C16: =SUMIFS(Detalle!$K$2:$K$326,Detalle!$Q$2:$Q$326,B16)
B17: TOTAL | C17: =SUM(C14:C16)

Sheet Detalle
A1: Fecha | B1: No OC | C1: No pedido | D1: Estado | E1: Legalización | F1: Grupo | G1: Sub grupo | H1: Producto / servicio | I1: Cant. | J1: Precio unit. | K1: Valor sin IVA | L1: Tipo impuesto | M1: IVA | N1: Total con IVA | O1: Solicitó | P1: Proveedor | Q1: Tipo solicitud | R1: Tipo proyecto | S1: No factura | T1: Categoría de ítem
A2: 46259.466 | B2: 3975 | C2: 3083 | D2: CERRADA | E2: PAGADA | F2: Servicio | G2: Retie | H2: CORTE EN ACRILICO - UND | I2: 1 | J2: 1554400 | K2: 1554400 | M2: 0 | N2: =K2+M2 | O2: LAURA SOFIA SALAS ROSERO | P2: ANGELICA MARIA AGREDA AGREDA | Q2: PLANEADA | R2: MINI GRANJAS | S2: FE1592 | T2: Servicios de obra e ingeniería
A3: 46259.465 | B3: 3973 | C3: 3078 | D3: CERRADA | E3: PAGADA | F3: Servicio | G3: Retie | H3: CORTE EN ACRILICO - UND | I3: 1 | J3: 114000 | K3: 114000 | M3: 0 | N3: =K3+M3 | O3: LAURA SOFIA SALAS ROSERO | P3: ANGELICA MARIA AGREDA AGREDA | Q3: PLANEADA | R3: MINI GRANJAS | S3: FE1607 | T3: Servicios de obra e ingeniería
A4: 46259.464 | B4: 3972 | C4: 3075 | D4: CERRADA | E4: PAGADA | F4: Servicio | G4: Retie | H4: CORTE EN ACRILICO - UND | I4: 1 | J4: 178000 | K4: 178000 | M4: 0 | N4: =K4+M4 | O4: LAURA SOFIA SALAS ROSERO | P4: ANGELICA MARIA AGREDA AGREDA | Q4: PLANEADA | R4: MINI GRANJAS | S4: FE1613 | T4: Servicios de obra e ingeniería
A5: 46258.516 | B5: 3961 | C5: 3060 | D5: CERRADA | E5: PAGADA | F5: Servicio | G5: Retie | H5: CORTE EN ACRILICO - UND | I5: 1 | J5: 63400 | K5: 63400 | M5: 0 | N5: =K5+M5 | O5: LAURA SOFIA SALAS ROSERO | P5: ANGELICA MARIA AGREDA AGREDA | Q5: PLANEADA | R5: MINI GRANJAS | S5: FACTURA ELECTRONICA DE VENTA FE 1632 | T5: Servicios de obra e ingeniería
A6: 46248.669 | B6: 3866 | C6: 2986 | D6: CERRADA | E6: PAGADA | F6: Servicio | G6: Baños Portátiles | H6: ALQUILER DE BAÑO PORTATIL - UND | I6: 1 | J6: 1721600 | K6: 1721600 | M6: 0 | N6: =K6+M6 | O6: LAURA SOFIA SALAS ROSERO | P6: HOOVER ANTONIO GUACHAVES LASSO | Q6: PLANEADA | R6: MINI GRANJAS | S6: Número de Factura: FEV-115 | T6: Baños y sanitarios portátiles
A7: 46248.667 | B7: 3860 | C7: 2946 | D7: CERRADA | E7: CAUSADA | F7: Servicio | G7: Preparativos Previos Inicio De Obras | H7: EXAMEN PERIODICO - UND | I7: 1 | J7: 32000 | K7: 32000 | M7: 0 | N7: =K7+M7 | O7: LAURA SOFIA SALAS ROSERO | P7: IPS BIENESTAR LABORAL SAS | Q7: URGENCIA | R7: MINI GRANJAS | S7: N 4417 | T7: SST y exámenes médicos
A8: 46237.455 | B8: 3697 | C8: 2812 | D8: CERRADA | E8: PAGADA | F8: Servicio | G8: Logística Viáticos | H8: SERVICIO DE RESTAURANTE - UND | I8: 39 | J8: 10362.69 | K8: 404144.91 | M8: 0 | N8: =K8+M8 | O8: LAURA SOFIA SALAS ROSERO | P8: MAYERLINE TOBAR GOMEZ | Q8: PLANEADA | R8: MINI GRANJAS | S8: FE 1876 | T8: Viáticos - Alimentación
A9: 46237.455 | B9: 3697 | C9: 2812 | D9: CERRADA | E9: PAGADA | F9: Servicio | G9: Logística Viáticos | H9: SERVICIO DE RESTAURANTE - UND | I9: 69 | J9: 13471.51 | K9: 929534.19 | M9: 0 | N9: =K9+M9 | O9: LAURA SOFIA SALAS ROSERO | P9: MAYERLINE TOBAR GOMEZ | Q9: PLANEADA | R9: MINI GRANJAS | S9: FE 1876 | T9: Viáticos - Alimentación
A10: 46234.376 | B10: 3672 | C10: 2747 | D10: CERRADA | E10: PAGADA | F10: Servicio | G10: Logística Viáticos | H10: SERVICIO DE HOTEL - UND | I10: 11 | J10: 36270 | K10: 398970 | M10: 0 | N10: =K10+M10 | O10: LAURA SOFIA SALAS ROSERO | P10: MAYERLINE TOBAR GOMEZ | Q10: PLANEADA | R10: MINI GRANJAS | S10: FE 1884 | T10: Viáticos - Hospedaje
A11: 46234.376 | B11: 3672 | C11: 2747 | D11: CERRADA | E11: PAGADA | F11: Servicio | G11: Logística Viáticos | H11: SERVICIO DE HOTEL - UND | I11: 1 | J11: 621762 | K11: 621762 | M11: 0 | N11: =K11+M11 | O11: LAURA SOFIA SALAS ROSERO | P11: MAYERLINE TOBAR GOMEZ | Q11: PLANEADA | R11: MINI GRANJAS | S11: FE 1884 | T11: Viáticos - Hospedaje
A12: 46225.596 | B12: 3556 | C12: 2705 | D12: CERRADA | E12: PAGADA | F12: Servicio | G12: Baños Portátiles | H12: ALQUILER DE BAÑO PORTATIL - UND | I12: 1 | J12: 1721600 | K12: 1721600 | M12: 0 | N12: =K12+M12 | O12: LAURA SOFIA SALAS ROSERO | P12: HOOVER ANTONIO GUACHAVES LASSO | Q12: URGENCIA | R12: MINI GRANJAS | S12: FEV 101 | T12: Baños y sanitarios portátiles
A13: 46220.442 | B13: 3533 | C13: 2673 | D13: CERRADA | E13: CAUSADA | F13: Servicio | G13: Set (Electrico)Servicio | H13: PRUEBAS DE RUTINA EN SITIO A SISTEMAS DE MEDICION NIVEL 2 PARA TC´s Y TP´s - UND | I13: 1 | J13: 5880000 | K13: 5880000 | L13: IVA 19% | M13: 1117200 | N13: =K13+M13 | O13: LAURA SOFIA SALAS ROSERO | P13: NEGAWATT S.A.S | Q13: PLANEADA | R13: MINI GRANJAS | S13: COT-479 | T13: RETIE / Legalización / Medición
A14: 46211.68 | B14: 3440 | C14: 2614 | D14: CERRADA | E14: PAGADA | F14: Servicio | G14: Logística Viáticos | H14: SERVICIO DE RESTAURANTE - UND | I14: 31 | J14: 10362.69 | K14: 321243.39 | M14: 0 | N14: =K14+M14 | O14: LAURA SOFIA SALAS ROSERO | P14: MAYERLINE TOBAR GOMEZ | Q14: PLANEADA | R14: MINI GRANJAS | S14: FE1841 | T14: Viáticos - Alimentación
A15: 46211.68 | B15: 3440 | C15: 2614 | D15: CERRADA | E15: PAGADA | F15: Servicio | G15: Logística Viáticos | H15: SERVICIO DE RESTAURANTE - UND | I15: 61 | J15: 13471.51 | K15: 821762.11 | M15: 0 | N15: =K15+M15 | O15: LAURA SOFIA SALAS ROSERO | P15: MAYERLINE TOBAR GOMEZ | Q15: PLANEADA | R15: MINI GRANJAS | S15: FE1841 | T15: Viáticos - Alimentación
A16: 46205.474 | B16: 3414 | C16: 2579 | D16: CERRADA | E16: PAGADA | F16: Servicio | G16: Logística Viáticos | H16: SERVICIO DE COMEDOR / RESTAURANTE - UND | I16: 36 | J16: 10362.69 | K16: 373056.84 | M16: 0 | N16: =K16+M16 | O16: LAURA SOFIA SALAS ROSERO | P16: MAYERLINE TOBAR GOMEZ | Q16: PLANEADA | R16: MINI GRANJAS | S16: FE1818 | T16: Viáticos - Alimentación
A17: 46205.474 | B17: 3414 | C17: 2579 | D17: CERRADA | E17: PAGADA | F17: Servicio | G17: Logística Viáticos | H17: SERVICIO DE RESTAURANTE - UND | I17: 70 | J17: 13471.51 | K17: 943005.7 | M17: 0 | N17: =K17+M17 | O17: LAURA SOFIA SALAS ROSERO | P17: MAYERLINE TOBAR GOMEZ | Q17: PLANEADA | R17: MINI GRANJAS | S17: FE1818 | T17: Viáticos - Alimentación
A18: 46205.455 | B18: 3409 | C18: 2581 | D18: CERRADA | E18: PAGADA | F18: Servicio | G18: Logística Viáticos | H18: SERVICIO DE HOTEL - UND | I18: 3 | J18: 518134.72 | K18: 1554404.2 | M18: 0 | N18: =K18+M18 | O18: LAURA SOFIA SALAS ROSERO | P18: MAYERLINE TOBAR GOMEZ | Q18: PLANEADA | R18: MINI GRANJAS | S18: FE1832 | T18: Viáticos - Hospedaje
A19: 46192.389 | B19: 3330 | C19: 2502 | D19: CERRADA | E19: PAGADA | F19: C. Canalizaciones | G19: Instalación De Tuberías Ac, Dc Y Tierra | H19: CURVA 1" PVC NACIONAL CONDUIT (90°/1 CAMPANA)- TUBOSA/IMEC 1302-160807 - UND | I19: 30 | J19: 1058.7 | K19: 31761 | L19: IVA 19% | M19: 6034 | N19: =K19+M19 | O19: LAURA SOFIA SALAS ROSERO | P19: ELECTRICOS DEL VALLE SAS | Q19: EMERGENCIA | R19: MINI GRANJAS | S19: EPE25355 | T19: Canalización y tubería
A20: 46192.389 | B20: 3330 | C20: 2502 | D20: CERRADA | E20: PAGADA | F20: C. Canalizaciones | G20: Instalación De Tuberías Ac, Dc Y Tierra | H20: CAPACETE 1" IMC GALVANIZADO E.V SOLUTIONS - UND | I20: 8 | J20: 3645.1 | K20: 29160.8 | L20: IVA 19% | M20: 5540 | N20: =K20+M20 | O20: LAURA SOFIA SALAS ROSERO | P20: ELECTRICOS DEL VALLE SAS | Q20: EMERGENCIA | R20: MINI GRANJAS | S20: EPE25355 | T20: Otros / sin clasificar
A21: 46192.389 | B21: 3330 | C21: 2502 | D21: CERRADA | E21: PAGADA | F21: C. Canalizaciones | G21: Instalación De Tuberías Ac, Dc Y Tierra | H21: TUBO 1" PVC COUNDUIT 3 MTS 1302-160905 - UND | I21: 110 | J21: 5840.4 | K21: 642444 | L21: IVA 19% | M21: 122064 | N21: =K21+M21 | O21: LAURA SOFIA SALAS ROSERO | P21: ELECTRICOS DEL VALLE SAS | Q21: EMERGENCIA | R21: MINI GRANJAS | S21: EPE25355 | T21: Canalización y tubería
A22: 46192.389 | B22: 3330 | C22: 2502 | D22: CERRADA | E22: PAGADA | F22: C. Canalizaciones | G22: Instalación De Tuberías Ac, Dc Y Tierra | H22: TUBO 1" IMC GALV 3MTS 1301-160693 - UND | I22: 8 | J22: 29341.6 | K22: 234732.8 | L22: IVA 19% | M22: 44599 | N22: =K22+M22 | O22: LAURA SOFIA SALAS ROSERO | P22: ELECTRICOS DEL VALLE SAS | Q22: EMERGENCIA | R22: MINI GRANJAS | S22: EPE25355 | T22: Canalización y tubería
A23: 46183.52 | B23: 3242 | C23: 2449 | D23: CERRADA | E23: PAGADA | F23: Montaje Eléctrico | G23: Set (Electrico)Servicio | H23: DESCARGUE E INSTALACION DE CELDAS PARA TRANSFORMADORES MAS SERVICIO DE GRUA - UND | I23: 1 | J23: 1528000 | K23: 1528000 | M23: 0 | N23: =K23+M23 | O23: LAURA SOFIA SALAS ROSERO | P23: JOHN JAIRO CHAPAL ESTACIO | Q23: PLANEADA | R23: MINI GRANJAS | S23: FE-820 | T23: Fletes y transporte de carga
A24: 46183.518 | B24: 3238 | C24: 2419 | D24: CERRADA | E24: PAGADA | F24: Servicio | G24: Logística Viáticos | H24: SERVICIO DE RESTAURANTE - UND | I24: 45 | J24: 10362.69 | K24: 466321.05 | M24: 0 | N24: =K24+M24 | O24: LAURA SOFIA SALAS ROSERO | P24: MAYERLINE TOBAR GOMEZ | Q24: PLANEADA | R24: MINI GRANJAS | S24: 1781 | T24: Viáticos - Alimentación
A25: 46183.518 | B25: 3238 | C25: 2419 | D25: CERRADA | E25: PAGADA | F25: Servicio | G25: Logística Viáticos | H25: SERVICIO DE RESTAURANTE - UND | I25: 83 | J25: 13471.51 | K25: 1118135.3 | M25: 0 | N25: =K25+M25 | O25: LAURA SOFIA SALAS ROSERO | P25: MAYERLINE TOBAR GOMEZ | Q25: PLANEADA | R25: MINI GRANJAS | S25: 1781 | T25: Viáticos - Alimentación
A26: 46183.518 | B26: 3237 | C26: 2421 | D26: CERRADA | E26: PAGADA | F26: Set (Civil) Suministro | G26: Set (Civil) Servicio | H26: RECEBO - M3 | I26: 14 | J26: 85000 | K26: 1190000 | M26: 0 | N26: =K26+M26 | O26: LAURA SOFIA SALAS ROSERO | P26: CAMPO HELMER PORTILLO PORTILLA | Q26: PLANEADA | R26: MINI GRANJAS | S26: 0255 | T26: Obra civil (concreto, agregados)
A27: 46183.518 | B27: 3237 | C27: 2421 | D27: CERRADA | E27: PAGADA | F27: Servicio | G27: Preparativos Previos Inicio De Obras | H27: ARENA DE RIO METRO CUBICO - UND | I27: 7 | J27: 90000 | K27: 630000 | M27: 0 | N27: =K27+M27 | O27: LAURA SOFIA SALAS ROSERO | P27: CAMPO HELMER PORTILLO PORTILLA | Q27: PLANEADA | R27: MINI GRANJAS | S27: 0255 | T27: Obra civil (concreto, agregados)
A28: 46178.441 | B28: 3190 | C28: 2385 | D28: CERRADA | E28: PAGADA | F28: Servicio | G28: Logística Viáticos | H28: SERVICIO DE HOTEL - UND | I28: 3 | J28: 518135 | K28: 1554405 | M28: 0 | N28: =K28+M28 | O28: LAURA SOFIA SALAS ROSERO | P28: MAYERLINE TOBAR GOMEZ | Q28: PLANEADA | R28: MINI GRANJAS | S28: 1744 | T28: Viáticos - Hospedaje
A29: 46170.629 | B29: 3128 | C29: 2331 | D29: GENERADA | E29: PENDIENTE | F29: Set (Electrico) Suministro | G29: Set (Electrico)Servicio | H29: SERVICIO DE TRANSPORTE - UND | I29: 1 | J29: 16806 | K29: 16806 | L29: IVA 19% | M29: 3193 | N29: =K29+M29 | O29: LAURA SOFIA SALAS ROSERO | P29: HUMBERTO JAVIER ROSERO POTOSI | Q29: PLANEADA | R29: MINI GRANJAS | T29: Viáticos - Transporte
A30: 46170.629 | B30: 3128 | C30: 2331 | D30: GENERADA | E30: PENDIENTE | F30: Set (Electrico) Suministro | G30: Set (Electrico)Servicio | H30: SUMINISTRO DE TAPA METÁLICA DE 0.25 X 0.28 MTS PARA CAJA DE INSPECCIÓN EN LÁMINA ALFAJOR DE 2.5MM, ANGULO DE 1 1/2X3/16, PINTURA ANTICORROSIVA Y ESMALTE. - UND | I30: 2 | J30: 96639 | K30: 193278 | L30: IVA 19% | M30: 36722 | N30: =K30+M30 | O30: LAURA SOFIA SALAS ROSERO | P30: HUMBERTO JAVIER ROSERO POTOSI | Q30: PLANEADA | R30: MINI GRANJAS | T30: RETIE / Legalización / Medición
A31: 46170.628 | B31: 3127 | C31: 2348 | D31: CERRADA | E31: CAUSADA | F31: Cajas De Paso | G31: Transportes | H31: SERVICIO DE TRANSPORTE - UND | I31: 1 | J31: 50000 | K31: 50000 | M31: 0 | N31: =K31+M31 | O31: LAURA SOFIA SALAS ROSERO | P31: HUMBERTO JAVIER ROSERO POTOSI | Q31: PLANEADA | R31: MINI GRANJAS | S31: FEHJ 36 | T31: Viáticos - Transporte
A32: 46170.628 | B32: 3127 | C32: 2348 | D32: CERRADA | E32: CAUSADA | F32: Cajas De Paso | G32: (Sin Subgrupo) | H32: SUMINISTRO DE MARCOS METÁLICOS PARA CAJA DE INSPECCIÓN , PINTURA ANTICORROSIVA Y ESMALTE NEGRO EN ÁNGULO 1 1/2X3/16" CON DIMENSIONES: ANCHO: 1.5 M - LARGO: 1.5 M - UND | I32: 1 | J32: 162185 | K32: 162185 | L32: IVA 19% | M32: 30815 | N32: =K32+M32 | O32: LAURA SOFIA SALAS ROSERO | P32: HUMBERTO JAVIER ROSERO POTOSI | Q32: PLANEADA | R32: MINI GRANJAS | S32: FEHJ 36 | T32: RETIE / Legalización / Medición
A33: 46170.628 | B33: 3127 | C33: 2348 | D33: CERRADA | E33: CAUSADA | F33: Cajas De Paso | G33: (Sin Subgrupo) | H33: SUMINISTRO DE TAPAS METÁLICAS PARA CAJA DE INSPECCIÓN EN LÁMINA ALFAJOR DE 2.5 MM, ÁNGULO DE 1 ½ X 3/16", PINTURA ANTICORROSIVA Y ESMALTE. DIMENSIONES: ANCHO: 1.5M Y LARGO: 1.5M - UND | I33: 1 | J33: 794118 | K33: 794118 | L33: IVA 19% | M33: 150882 | N33: =K33+M33 | O33: LAURA SOFIA SALAS ROSERO | P33: HUMBERTO JAVIER ROSERO POTOSI | Q33: PLANEADA | R33: MINI GRANJAS | S33: FEHJ 36 | T33: RETIE / Legalización / Medición
A34: 46170.621 | B34: 3119 | C34: 2328 | D34: CERRADA | E34: PAGADA | F34: Servicio | G34: Logística Viáticos | H34: SERVICIO DE RESTAURANTE - UND | I34: 38 | J34: 10362.7 | K34: 393782.6 | M34: 0 | N34: =K34+M34 | O34: LAURA SOFIA SALAS ROSERO | P34: MAYERLINE TOBAR GOMEZ | Q34: URGENCIA | R34: MINI GRANJAS | S34: 1728 | T34: Viáticos - Alimentación
A35: 46170.621 | B35: 3119 | C35: 2328 | D35: CERRADA | E35: PAGADA | F35: Servicio | G35: Logística Viáticos | H35: SERVICIO DE RESTAURANTE - UND | I35: 68 | J35: 13471.5 | K35: 916062 | M35: 0 | N35: =K35+M35 | O35: LAURA SOFIA SALAS ROSERO | P35: MAYERLINE TOBAR GOMEZ | Q35: URGENCIA | R35: MINI GRANJAS | S35: 1728 | T35: Viáticos - Alimentación
A36: 46156.703 | B36: 2943 | C36: 2207 | D36: CERRADA | E36: PAGADA | F36: 9-Legalización | G36: 9.1 -Retie Gd | H36: CERTIFICADO RETIE - UND | I36: 1 | J36: 1000000 | K36: 1000000 | L36: IVA 19% | M36: 190000 | N36: =K36+M36 | O36: LAURA SOFIA SALAS ROSERO | P36: ODIR CERTIFICACIONES SAS | Q36: EMERGENCIA | R36: MINI GRANJAS | S36: ODIR-016201 | T36: RETIE / Legalización / Medición
A37: 46155.427 | B37: 2925 | C37: 2159 | D37: CERRADA | E37: PAGADA | F37: Set (Electrico) Suministro | G37: (Sin Subgrupo) | H37: SENSOR DE HUMO LYNX SECURITY LY-DH4T - UND | I37: 2 | J37: 58000 | K37: 116000 | L37: IVA 19% | M37: 22040 | N37: =K37+M37 | O37: LAURA SOFIA SALAS ROSERO | P37: SEGURIDAD DEL SUR LIMITADA | Q37: PLANEADA | R37: MINI GRANJAS | S37: 002 | T37: Otros / sin clasificar
A38: 46155.426 | B38: 2924 | C38: 2159 | D38: CERRADA | E38: CAUSADA | F38: Set (Electrico) Suministro | G38: (Sin Subgrupo) | H38: EXTINTOR TIPO CO2 CLASE BC X 10LB (ACERO) - UND | I38: 2 | J38: 250000 | K38: 500000 | L38: IVA 19% | M38: 95000 | N38: =K38+M38 | O38: LAURA SOFIA SALAS ROSERO | P38: DISTRITO E SAS | Q38: PLANEADA | R38: MINI GRANJAS | S38: 2155 | T38: Otros / sin clasificar
A39: 46155.42 | B39: 2919 | C39: 2164 | D39: CERRADA | E39: PAGADA | F39: Servicio | G39: Logística Viáticos | H39: SERVICIO DE RESTAURANTE - UND | I39: 38 | J39: 10362.69 | K39: 393782.22 | M39: 0 | N39: =K39+M39 | O39: LAURA SOFIA SALAS ROSERO | P39: MAYERLINE TOBAR GOMEZ | Q39: PLANEADA | R39: MINI GRANJAS | S39: 1709 | T39: Viáticos - Alimentación
A40: 46155.42 | B40: 2919 | C40: 2164 | D40: CERRADA | E40: PAGADA | F40: Servicio | G40: Logística Viáticos | H40: SERVICIO DE RESTAURANTE - UND | I40: 67 | J40: 13471.51 | K40: 902591.17 | M40: 0 | N40: =K40+M40 | O40: LAURA SOFIA SALAS ROSERO | P40: MAYERLINE TOBAR GOMEZ | Q40: PLANEADA | R40: MINI GRANJAS | S40: 1709 | T40: Viáticos - Alimentación
A41: 46155.419 | B41: 2918 | C41: 2165 | D41: CERRADA | E41: CAUSADA | F41: Set (Civil) Suministro | G41: Set (Civil) Servicio | H41: SERVICIO DE TRANSPORTE - UND | I41: 1 | J41: 630251 | K41: 630251 | M41: 0 | N41: =K41+M41 | O41: LAURA SOFIA SALAS ROSERO | P41: HUMBERTO JAVIER ROSERO POTOSI | Q41: PLANEADA | R41: MINI GRANJAS | S41: FEHJ39 | T41: Viáticos - Transporte
A42: 46155.419 | B42: 2918 | C42: 2165 | D42: CERRADA | E42: CAUSADA | F42: Set (Civil) Suministro | G42: Set (Civil) Servicio | H42: SUMINISTRO DE TAPAS PARA CÁRCAMOS. CUARTO ELÉCTRICO. EN ANGULO DE 1 1/4X1/8" Y LAMINA ALFAJOR DE 2.5MM, PINTURA ANTICORROSIVA Y ESMALTE. - UND | I42: 1 | J42: 4396840.8 | K42: 4396840.8 | M42: 0 | N42: =K42+M42 | O42: LAURA SOFIA SALAS ROSERO | P42: HUMBERTO JAVIER ROSERO POTOSI | Q42: PLANEADA | R42: MINI GRANJAS | S42: FEHJ39 | T42: Estructura y soportería solar
A43: 46155.416 | B43: 2914 | C43: 2169 | D43: CERRADA | E43: PAGADA | F43: Servicio | G43: Preparativos Previos Inicio De Obras | H43: CHIPA DE ACERO 3/8 CORRUGADA - UND | I43: 300 | J43: 4453.7 | K43: 1336110 | L43: IVA 19% | M43: 253860 | N43: =K43+M43 | O43: LAURA SOFIA SALAS ROSERO | P43: LIBIA MIREYA ROSERO DAZA (FERRETERIA EL BORDO) | Q43: PLANEADA | R43: MINI GRANJAS | S43: 7148 | T43: Obra civil (concreto, agregados)
A44: 46153.67 | B44: 2898 | C44: 2159 | D44: CERRADA | E44: PAGADA | F44: Set (Electrico) Suministro | G44: (Sin Subgrupo) | H44: SIKABOOM - UND | I44: 10 | J44: 54171 | K44: 541710 | L44: IVA 19% | M44: 102924 | N44: =K44+M44 | O44: LAURA SOFIA SALAS ROSERO | P44: GRUPO EMPRESARIAL SILVER S.A.S | Q44: PLANEADA | R44: MINI GRANJAS | S44: 003 | T44: Impermeabilización y acabados
A45: 46150.634 | B45: 2884 | C45: 2132 | D45: CERRADA | E45: PAGADA | F45: C. Material Micropilotaje | G45: (Sin Subgrupo) | H45: CRUDO DE RÍO X M3 - M3 | I45: 35 | J45: 90000 | K45: 3150000 | M45: 0 | N45: =K45+M45 | O45: LAURA SOFIA SALAS ROSERO | P45: CAMPO HELMER PORTILLO PORTILLA | Q45: PLANEADA | R45: MINI GRANJAS | S45: 0248 | T45: Obra civil (concreto, agregados)
A46: 46150.632 | B46: 2882 | C46: 2134 | D46: CERRADA | E46: PAGADA | F46: Cajas De Paso | G46: (Sin Subgrupo) | H46: TRITURADO 3/4 - M3 | I46: 14 | J46: 164000 | K46: 2296000 | M46: 0 | N46: =K46+M46 | O46: LAURA SOFIA SALAS ROSERO | P46: CAMPO HELMER PORTILLO PORTILLA | Q46: PLANEADA | R46: MINI GRANJAS | S46: 0247 | T46: Obra civil (concreto, agregados)
A47: 46150.625 | B47: 2874 | C47: 2124 | D47: CERRADA | E47: PAGADA | F47: Servicio | G47: Set (Electrico)Servicio | H47: INSTALACION PREMOLDEADOS - UND | I47: 12 | J47: 134453.78 | K47: 1613445.4 | L47: IVA 19% | M47: 306554 | N47: =K47+M47 | O47: LAURA SOFIA SALAS ROSERO | P47: CONSTRUELECTRIC CNE SAS | Q47: PLANEADA | R47: MINI GRANJAS | S47: No. FVE 43 | T47: Servicios de instalación y montaje
A48: 46148.436 | B48: 2845 | C48: 2114 | D48: CERRADA | E48: PAGADA | F48: Servicio | G48: Set (Electrico)Servicio | H48: SERVICIO DE COMISIONAMIENTO Y ACOMPAÑAMIENTO EN LA ENERGIZACIÓN - UND | I48: 1 | J48: 17970000 | K48: 17970000 | M48: 0 | N48: =K48+M48 | O48: LAURA SOFIA SALAS ROSERO | P48: DAGELEC LTDA | Q48: URGENCIA | R48: MINI GRANJAS | S48: OF-162-2026 | T48: Servicios de obra e ingeniería
A49: 46146.636 | B49: 2825 | C49: 2106 | D49: CERRADA | E49: PAGADA | F49: Set (Civil) Suministro | G49: Set (Civil) Servicio | H49: OMEGA PARA INSTALACION DE SUPERBOARD ( 0.38 MM X 3/4" X 2-5/16" X 2.44 METROS) - UND | I49: 30 | J49: 4000 | K49: 120000 | M49: 0 | N49: =K49+M49 | O49: LAURA SOFIA SALAS ROSERO | P49: AURA MIREY BURBANO DAZA (FERROMAC) | Q49: URGENCIA | R49: MINI GRANJAS | S49: 3622 | T49: Servicios de instalación y montaje
A50: 46146.636 | B50: 2825 | C50: 2106 | D50: CERRADA | E50: PAGADA | F50: Set (Civil) Suministro | G50: Set (Civil) Servicio | H50: VIGUETA PARA SUPERBOARD DE 1 1/2" X3/4" CALIBRE 40 - UND | I50: 15 | J50: 4000 | K50: 60000 | M50: 0 | N50: =K50+M50 | O50: LAURA SOFIA SALAS ROSERO | P50: AURA MIREY BURBANO DAZA (FERROMAC) | Q50: URGENCIA | R50: MINI GRANJAS | S50: 3622 | T50: Estructura y soportería solar
A51: 46146.636 | B51: 2825 | C51: 2106 | D51: CERRADA | E51: PAGADA | F51: Set (Civil) Suministro | G51: Set (Civil) Servicio | H51: PERFIL RECTANGULAR DE 2"X1" X 6M CAL 18 - UND | I51: 15 | J51: 40000 | K51: 600000 | M51: 0 | N51: =K51+M51 | O51: LAURA SOFIA SALAS ROSERO | P51: AURA MIREY BURBANO DAZA (FERROMAC) | Q51: URGENCIA | R51: MINI GRANJAS | S51: 3622 | T51: Estructura y soportería solar
A52: 46146.636 | B52: 2825 | C52: 2106 | D52: CERRADA | E52: PAGADA | F52: Set (Civil) Suministro | G52: Set (Civil) Servicio | H52: SOLDADURA PVC VERDEV 1/4 (S-29) UND GERFOR - UND | I52: 1 | J52: 56923 | K52: 56923 | M52: 0 | N52: =K52+M52 | O52: LAURA SOFIA SALAS ROSERO | P52: AURA MIREY BURBANO DAZA (FERROMAC) | Q52: URGENCIA | R52: MINI GRANJAS | S52: 3622 | T52: Otros / sin clasificar
A53: 46146.636 | B53: 2825 | C53: 2106 | D53: CERRADA | E53: PAGADA | F53: Set (Civil) Suministro | G53: Set (Civil) Servicio | H53: SUPERBOARD ESTANDAR 1220X2440X6MM (DP) UND SUPERBOAR - UND | I53: 20 | J53: 72000 | K53: 1440000 | M53: 0 | N53: =K53+M53 | O53: LAURA SOFIA SALAS ROSERO | P53: AURA MIREY BURBANO DAZA (FERROMAC) | Q53: URGENCIA | R53: MINI GRANJAS | S53: 3622 | T53: Estructura y soportería solar
A54: 46146.395 | B54: 2808 | C54: 2090 | D54: CERRADA | E54: PAGADA | F54: Servicio | G54: Set (Electrico)Servicio | H54: SERVICIO DE COMISIONAMIENTO Y ACOMPAÑAMIENTO EN LA ENERGIZACIÓN - UND | I54: 1 | J54: 3629842 | K54: 3629842 | L54: IVA 19% | M54: 689669 | N54: =K54+M54 | O54: LAURA SOFIA SALAS ROSERO | P54: NACIONAL DE TRANSFORMADORES S.A.S (TESLA) | Q54: URGENCIA | R54: MINI GRANJAS | S54: V001-2-008 | T54: Servicios de obra e ingeniería
A55: 46141.705 | B55: 2805 | C55: 2071 | D55: CERRADA | E55: PAGADA | F55: Servicio | G55: Logística Viáticos | H55: SERVICIO DE RESTAURANTE - UND | I55: 37 | J55: 10362.69 | K55: 383419.53 | M55: 0 | N55: =K55+M55 | O55: LAURA SOFIA SALAS ROSERO | P55: MAYERLINE TOBAR GOMEZ | Q55: PLANEADA | R55: MINI GRANJAS | S55: FE 1672 | T55: Viáticos - Alimentación
A56: 46141.705 | B56: 2805 | C56: 2071 | D56: CERRADA | E56: PAGADA | F56: Servicio | G56: Logística Viáticos | H56: SERVICIO DE RESTAURANTE - UND | I56: 72 | J56: 13471.51 | K56: 969948.72 | M56: 0 | N56: =K56+M56 | O56: LAURA SOFIA SALAS ROSERO | P56: MAYERLINE TOBAR GOMEZ | Q56: PLANEADA | R56: MINI GRANJAS | S56: FE 1672 | T56: Viáticos - Alimentación
A57: 46141.698 | B57: 2802 | C57: 2074 | D57: CERRADA | E57: PAGADA | F57: Servicio | G57: Logística Viáticos | H57: SERVICIO DE HOTEL - UND | I57: 1 | J57: 518134.72 | K57: 518134.72 | M57: 0 | N57: =K57+M57 | O57: LAURA SOFIA SALAS ROSERO | P57: MAYERLINE TOBAR GOMEZ | Q57: PLANEADA | R57: MINI GRANJAS | S57: FE 1681 | T57: Viáticos - Hospedaje
A58: 46141.698 | B58: 2802 | C58: 2074 | D58: CERRADA | E58: PAGADA | F58: Servicio | G58: Logística Viáticos | H58: SERVICIO DE HOTEL - UND | I58: 1 | J58: 621761.66 | K58: 621761.66 | M58: 0 | N58: =K58+M58 | O58: LAURA SOFIA SALAS ROSERO | P58: MAYERLINE TOBAR GOMEZ | Q58: PLANEADA | R58: MINI GRANJAS | S58: FE 1681 | T58: Viáticos - Hospedaje
A59: 46139.568 | B59: 2763 | C59: 2056 | D59: CERRADA | E59: PAGADA | F59: Servicio | G59: Descargues | H59: MONTACARGAS - UND | I59: 1 | J59: 21000000 | K59: 21000000 | M59: 0 | N59: =K59+M59 | O59: LAURA SOFIA SALAS ROSERO | P59: JASSON ALBEIRO VALENCIA ROSERO | Q59: PLANEADA | R59: MINI GRANJAS | S59: FEV30 | T59: Fletes y transporte de carga
A60: 46134.642 | B60: 2731 | C60: 2039 | D60: GENERADA | E60: PENDIENTE | F60: Set (Electrico) Suministro | G60: (Sin Subgrupo) | H60: TERMINAL TIPO FERRUL 10 AWG - UND | I60: 300 | J60: 93.17 | K60: 27951 | L60: IVA 19% | M60: 5310 | N60: =K60+M60 | O60: LAURA SOFIA SALAS ROSERO | P60: ELECTRICOS DEL VALLE SAS | Q60: PLANEADA | R60: MINI GRANJAS | T60: Cableado y conductores
A61: 46134.642 | B61: 2731 | C61: 2039 | D61: GENERADA | E61: PENDIENTE | F61: Set (Electrico) Suministro | G61: (Sin Subgrupo) | H61: GRAPA DOBLE ALA 3/4" - UND | I61: 30 | J61: 143.23 | K61: 4296.9 | L61: IVA 19% | M61: 816 | N61: =K61+M61 | O61: LAURA SOFIA SALAS ROSERO | P61: ELECTRICOS DEL VALLE SAS | Q61: PLANEADA | R61: MINI GRANJAS | T61: Cajas de paso y accesorios
A62: 46134.642 | B62: 2731 | C62: 2039 | D62: GENERADA | E62: PENDIENTE | F62: Set (Electrico) Suministro | G62: (Sin Subgrupo) | H62: GRAPA DOBLE ALA 1/2" - UND | I62: 30 | J62: 157.06 | K62: 4711.8 | L62: IVA 19% | M62: 895 | N62: =K62+M62 | O62: LAURA SOFIA SALAS ROSERO | P62: ELECTRICOS DEL VALLE SAS | Q62: PLANEADA | R62: MINI GRANJAS | T62: Cajas de paso y accesorios
A63: 46134.642 | B63: 2731 | C63: 2039 | D63: GENERADA | E63: PENDIENTE | F63: Set (Electrico) Suministro | G63: (Sin Subgrupo) | H63: TERMINAL ANILLO AMARILLO 12-10 AWG 1/4 - UND | I63: 15 | J63: 274.53 | K63: 4117.95 | L63: IVA 19% | M63: 782 | N63: =K63+M63 | O63: LAURA SOFIA SALAS ROSERO | P63: ELECTRICOS DEL VALLE SAS | Q63: PLANEADA | R63: MINI GRANJAS | T63: Cableado y conductores
A64: 46134.642 | B64: 2731 | C64: 2039 | D64: GENERADA | E64: PENDIENTE | F64: Set (Electrico) Suministro | G64: (Sin Subgrupo) | H64: CHAZO BALA 3/8" - UND | I64: 50 | J64: 291.84 | K64: 14592 | L64: IVA 19% | M64: 2772 | N64: =K64+M64 | O64: LAURA SOFIA SALAS ROSERO | P64: ELECTRICOS DEL VALLE SAS | Q64: PLANEADA | R64: MINI GRANJAS | T64: Cajas de paso y accesorios
A65: 46134.642 | B65: 2731 | C65: 2039 | D65: GENERADA | E65: PENDIENTE | F65: Set (Electrico) Suministro | G65: (Sin Subgrupo) | H65: TAPA CIEGA 4X4 PVC BLANCA - S/M - UND | I65: 10 | J65: 490.5 | K65: 4905 | L65: IVA 19% | M65: 931 | N65: =K65+M65 | O65: LAURA SOFIA SALAS ROSERO | P65: ELECTRICOS DEL VALLE SAS | Q65: PLANEADA | R65: MINI GRANJAS | T65: Cajas de paso y accesorios
A66: 46134.642 | B66: 2731 | C66: 2039 | D66: GENERADA | E66: PENDIENTE | F66: Set (Electrico) Suministro | G66: (Sin Subgrupo) | H66: UNION 1/2" IMC GALVANIZADA E.V SOLUTIONS 1301-RL-860 - UND | I66: 2 | J66: 498 | K66: 996 | L66: IVA 19% | M66: 189 | N66: =K66+M66 | O66: LAURA SOFIA SALAS ROSERO | P66: ELECTRICOS DEL VALLE SAS | Q66: PLANEADA | R66: MINI GRANJAS | T66: Otros / sin clasificar
A67: 46134.642 | B67: 2731 | C67: 2039 | D67: GENERADA | E67: PENDIENTE | F67: Set (Electrico) Suministro | G67: (Sin Subgrupo) | H67: TAPA PLASTICA PARA TOMA DOBLE BLANCA - UND | I67: 2 | J67: 561 | K67: 1122 | L67: IVA 19% | M67: 213 | N67: =K67+M67 | O67: LAURA SOFIA SALAS ROSERO | P67: ELECTRICOS DEL VALLE SAS | Q67: PLANEADA | R67: MINI GRANJAS | T67: Cajas de paso y accesorios
A68: 46134.642 | B68: 2731 | C68: 2039 | D68: GENERADA | E68: PENDIENTE | F68: Set (Electrico) Suministro | G68: (Sin Subgrupo) | H68: CAJA 4X4 PLASTICA DOBLE CP4X4 CERT -270 TERCOL - UND | I68: 2 | J68: 580.5 | K68: 1161 | L68: IVA 19% | M68: 220 | N68: =K68+M68 | O68: LAURA SOFIA SALAS ROSERO | P68: ELECTRICOS DEL VALLE SAS | Q68: PLANEADA | R68: MINI GRANJAS | T68: Cajas de paso y accesorios
A69: 46134.642 | B69: 2731 | C69: 2039 | D69: GENERADA | E69: PENDIENTE | F69: Set (Electrico) Suministro | G69: (Sin Subgrupo) | H69: UNION 1/2" EMT ACERO E.V - UND | I69: 25 | J69: 586.76 | K69: 14669 | L69: IVA 19% | M69: 2787 | N69: =K69+M69 | O69: LAURA SOFIA SALAS ROSERO | P69: ELECTRICOS DEL VALLE SAS | Q69: PLANEADA | R69: MINI GRANJAS | T69: Otros / sin clasificar
A70: 46134.642 | B70: 2731 | C70: 2039 | D70: GENERADA | E70: PENDIENTE | F70: Set (Electrico) Suministro | G70: (Sin Subgrupo) | H70: UNION 3/4" IMC GALVANIZADA - UND | I70: 2 | J70: 664.5 | K70: 1329 | L70: IVA 19% | M70: 252 | N70: =K70+M70 | O70: LAURA SOFIA SALAS ROSERO | P70: ELECTRICOS DEL VALLE SAS | Q70: PLANEADA | R70: MINI GRANJAS | T70: Otros / sin clasificar
A71: 46134.642 | B71: 2731 | C71: 2039 | D71: GENERADA | E71: PENDIENTE | F71: Set (Electrico) Suministro | G71: (Sin Subgrupo) | H71: ADAPTADOR 1/2"EMT - UND | I71: 20 | J71: 673 | K71: 13460 | L71: IVA 19% | M71: 2557 | N71: =K71+M71 | O71: LAURA SOFIA SALAS ROSERO | P71: ELECTRICOS DEL VALLE SAS | Q71: PLANEADA | R71: MINI GRANJAS | T71: Canalización y tubería
... A138: 46134.642 | B138: 2731 | C138: 2039 | D138: GENERADA | E138: PENDIENTE | F138: Set (Electrico) Suministro | G138: (Sin Subgrupo) | H138: ANALIZADOR DE ENERGÍA COMPACTO JANITZA UMG 103-CBM - UND | I138: 1 | J138: 1976925 | K138: 1976925 | L138: IVA 19% | M138: 375615 | N138: =K138+M138 | O138: LAURA SOFIA SALAS ROSERO | P138: ELECTRICOS DEL VALLE SAS | Q138: PLANEADA | R138: MINI GRANJAS | T138: Monitoreo y comunicaciones
A139: 46134.63 | B139: 2723 | C139: 2027 | D139: CERRADA | E139: PAGADA | F139: Montaje Eléctrico | G139: (Sin Subgrupo) | H139: MODEM ROUTER - UND | I139: 1 | J139: 670000 | K139: 670000 | L139: IVA 19% | M139: 127300 | N139: =K139+M139 | O139: LAURA SOFIA SALAS ROSERO | P139: EMSI TECHNOLOGIES COLOMBIA S.A.S | Q139: PLANEADA | R139: MINI GRANJAS | S139: E-4662 | T139: Monitoreo y comunicaciones
A140: 46133.701 | B140: 2709 | C140: 2014 | D140: CERRADA | E140: PAGADA | F140: Servicio | G140: Set (Electrico)Servicio | H140: CERTIFICACION DE FRONTERA COMERCIAL - UND | I140: 1 | J140: 5500000 | K140: 5500000 | L140: IVA 19% | M140: 1045000 | N140: =K140+M140 | O140: LAURA SOFIA SALAS ROSERO | P140: NEGAWATT S.A.S | Q140: PLANEADA | R140: MINI GRANJAS | S140: COT-394 | T140: RETIE / Legalización / Medición
A141: 46132.501 | B141: 2667 | C141: 1968 | D141: CERRADA | E141: PAGADA | F141: Servicio | G141: Baños Portátiles | H141: ALQUILER DE LAVAMANOS PORTATIL - UND | I141: 1 | J141: 40000 | K141: 40000 | M141: 0 | N141: =K141+M141 | O141: LAURA SOFIA SALAS ROSERO | P141: HOOVER ANTONIO GUACHAVES LASSO | Q141: PLANEADA | R141: MINI GRANJAS | S141: 031 | T141: Baños y sanitarios portátiles
A142: 46132.501 | B142: 2667 | C142: 1968 | D142: CERRADA | E142: PAGADA | F142: Servicio | G142: Baños Portátiles | H142: ALQUILER DE BAÑO PORTATIL - UND | I142: 1 | J142: 1681600 | K142: 1681600 | M142: 0 | N142: =K142+M142 | O142: LAURA SOFIA SALAS ROSERO | P142: HOOVER ANTONIO GUACHAVES LASSO | Q142: PLANEADA | R142: MINI GRANJAS | S142: 031 | T142: Baños y sanitarios portátiles
A143: 46132.498 | B143: 2665 | C143: 1965 | D143: CERRADA | E143: PAGADA | F143: Set (Electrico) Suministro | G143: Set (Electrico)Servicio | H143: MEDIDOR HEXING HXF300, ENERGÍA ACTIVA (CL0.5S) Y REACTIVA (CL2), 1(10)A, 57.7/100V - 277/480V, 60HZ, BIDIRECCIONAL, 1PUERTORS-232, 1PUERTORS-485 - UND | I143: 2 | J143: 1610000 | K143: 3220000 | L143: IVA 19% | M143: 611800 | N143: =K143+M143 | O143: LAURA SOFIA SALAS ROSERO | P143: INPEL S.A. | Q143: PLANEADA | R143: MINI GRANJAS | S143: COT-540 | T143: Medidores
A144: 46128.655 | B144: 2634 | C144: 1949 | D144: CERRADA | E144: CAUSADA | F144: Servicio | G144: Logística Viáticos | H144: SERVICIO DE RESTAURANTE - UND | I144: 57 | J144: 10362.69 | K144: 590673.33 | M144: 0 | N144: =K144+M144 | O144: LAURA SOFIA SALAS ROSERO | P144: MAYERLINE TOBAR GOMEZ | Q144: PLANEADA | R144: MINI GRANJAS | S144: 1645 | T144: Viáticos - Alimentación
A145: 46128.655 | B145: 2634 | C145: 1949 | D145: CERRADA | E145: CAUSADA | F145: Servicio | G145: Logística Viáticos | H145: SERVICIO DE RESTAURANTE - UND | I145: 95 | J145: 13471.51 | K145: 1279793.4 | M145: 0 | N145: =K145+M145 | O145: LAURA SOFIA SALAS ROSERO | P145: MAYERLINE TOBAR GOMEZ | Q145: PLANEADA | R145: MINI GRANJAS | S145: 1645 | T145: Viáticos - Alimentación
A146: 46125.619 | B146: 2596 | C146: 1932 | D146: CERRADA | E146: PAGADA | F146: Servicio | G146: Set (Electrico)Servicio | H146: CERTIFICADO RETIE - UND | I146: 1 | J146: 7500000 | K146: 7500000 | L146: IVA 19% | M146: 1425000 | N146: =K146+M146 | O146: LAURA SOFIA SALAS ROSERO | P146: ODIR CERTIFICACIONES SAS | Q146: EMERGENCIA | R146: MINI GRANJAS | S146: ODIR-014790 | T146: RETIE / Legalización / Medición
A147: 46125.43 | B147: 2581 | C147: 1919 | D147: CERRADA | E147: PAGADA | F147: Servicio | G147: Set (Electrico)Servicio | H147: DESCARGUE E INSTALACION DE CELDAS PARA TRANSFORMADORES MAS SERVICIO DE GRUA - UND | I147: 1 | J147: 2400000 | K147: 2400000 | M147: 0 | N147: =K147+M147 | O147: LAURA SOFIA SALAS ROSERO | P147: JOHN JAIRO CHAPAL ESTACIO | Q147: PLANEADA | R147: MINI GRANJAS | S147: FE-816 - | T147: Fletes y transporte de carga
A148: 46120.413 | B148: 2533 | C148: 1878 | D148: CERRADA | E148: PAGADA | F148: Set (Civil) Suministro | G148: (Sin Subgrupo) | H148: VINILO BLANCO TIPO 1 PINTULAND (SUPERLAVABLE PARA INTERIORES Y EXTERIORES) X CUÑETE - UND | I148: 2 | J148: 260504.2 | K148: 521008.4 | L148: IVA 19% | M148: 98992 | N148: =K148+M148 | O148: LAURA SOFIA SALAS ROSERO | P148: ALEXANDER ANGULO BURBANO | Q148: PLANEADA | R148: MINI GRANJAS | S148: cot 143 | T148: Impermeabilización y acabados
A149: 46118.36 | B149: 2488 | C149: 1865 | D149: CERRADA | E149: PAGADA | F149: Servicio | G149: Preparativos Previos Inicio De Obras | H149: RECEBO - M3 | I149: 30 | J149: 30000 | K149: 900000 | M149: 0 | N149: =K149+M149 | O149: JULIO CESAR DEAVILA MARTINEZ | P149: CAMPO HELMER PORTILLO PORTILLA | Q149: PLANEADA | R149: MINI GRANJAS | S149: 0237 | T149: Obra civil (concreto, agregados)
A150: 46118.36 | B150: 2488 | C150: 1865 | D150: CERRADA | E150: PAGADA | F150: Servicio | G150: Preparativos Previos Inicio De Obras | H150: CRUDO DE RÍO X M3 - M3 | I150: 210 | J150: 46000 | K150: 9660000 | M150: 0 | N150: =K150+M150 | O150: JULIO CESAR DEAVILA MARTINEZ | P150: CAMPO HELMER PORTILLO PORTILLA | Q150: PLANEADA | R150: MINI GRANJAS | S150: 0237 | T150: Obra civil (concreto, agregados)
A151: 46112.429 | B151: 2457 | C151: 1849 | D151: CERRADA | E151: CAUSADA | F151: Servicio | G151: Logística Viáticos | H151: SERVICIO DE RESTAURANTE - UND | I151: 63 | J151: 10362.69 | K151: 652849.47 | M151: 0 | N151: =K151+M151 | O151: LAURA SOFIA SALAS ROSERO | P151: MAYERLINE TOBAR GOMEZ | Q151: PLANEADA | R151: MINI GRANJAS | S151: 1600 | T151: Viáticos - Alimentación
A152: 46112.429 | B152: 2457 | C152: 1849 | D152: CERRADA | E152: CAUSADA | F152: Servicio | G152: Logística Viáticos | H152: SERVICIO DE RESTAURANTE - UND | I152: 58 | J152: 13471.5 | K152: 781347 | M152: 0 | N152: =K152+M152 | O152: LAURA SOFIA SALAS ROSERO | P152: MAYERLINE TOBAR GOMEZ | Q152: PLANEADA | R152: MINI GRANJAS | S152: 1600 | T152: Viáticos - Alimentación
A153: 46112.429 | B153: 2457 | C153: 1849 | D153: CERRADA | E153: CAUSADA | F153: Servicio | G153: Logística Viáticos | H153: SERVICIO DE RESTAURANTE - UND | I153: 64 | J153: 13471.51 | K153: 862176.64 | M153: 0 | N153: =K153+M153 | O153: LAURA SOFIA SALAS ROSERO | P153: MAYERLINE TOBAR GOMEZ | Q153: PLANEADA | R153: MINI GRANJAS | S153: 1600 | T153: Viáticos - Alimentación
A154: 46112.427 | B154: 2456 | C154: 1851 | D154: CERRADA | E154: PAGADA | F154: Servicio | G154: Logística Viáticos | H154: SERVICIO DE HOTEL - UND | I154: 2 | J154: 621761.66 | K154: 1243523.3 | M154: 0 | N154: =K154+M154 | O154: LAURA SOFIA SALAS ROSERO | P154: MAYERLINE TOBAR GOMEZ | Q154: PLANEADA | R154: MINI GRANJAS | S154: FE 1604 | T154: Viáticos - Hospedaje
A155: 46106.664 | B155: 2407 | C155: 1804 | D155: CERRADA | E155: PAGADA | F155: Servicio | G155: Logística Viáticos | H155: SERVICIO DE RESTAURANTE - UND | I155: 74 | J155: 10362.7 | K155: 766839.8 | M155: 0 | N155: =K155+M155 | O155: LAURA SOFIA SALAS ROSERO | P155: MAYERLINE TOBAR GOMEZ | Q155: PLANEADA | R155: MINI GRANJAS | S155: FE 1577 | T155: Viáticos - Alimentación
A156: 46106.664 | B156: 2407 | C156: 1804 | D156: CERRADA | E156: PAGADA | F156: Servicio | G156: Logística Viáticos | H156: SERVICIO DE RESTAURANTE - UND | I156: 65 | J156: 12435.23 | K156: 808289.95 | M156: 0 | N156: =K156+M156 | O156: LAURA SOFIA SALAS ROSERO | P156: MAYERLINE TOBAR GOMEZ | Q156: PLANEADA | R156: MINI GRANJAS | S156: FE 1577 | T156: Viáticos - Alimentación
A157: 46106.664 | B157: 2407 | C157: 1804 | D157: CERRADA | E157: PAGADA | F157: Servicio | G157: Logística Viáticos | H157: SERVICIO DE RESTAURANTE - UND | I157: 68 | J157: 12435.23 | K157: 845595.64 | M157: 0 | N157: =K157+M157 | O157: LAURA SOFIA SALAS ROSERO | P157: MAYERLINE TOBAR GOMEZ | Q157: PLANEADA | R157: MINI GRANJAS | S157: FE 1577 | T157: Viáticos - Alimentación
A158: 46106.651 | B158: 2400 | C158: 1801 | D158: CERRADA | E158: PAGADA | F158: C. Material Micropilotaje | G158: (Sin Subgrupo) | H158: CEMENTO GRIS X BULTO - UND | I158: 75 | J158: 35500 | K158: 2662500 | M158: 0 | N158: =K158+M158 | O158: LAURA SOFIA SALAS ROSERO | P158: ANDREA PATRICIA LASSO (FERROPAISA) | Q158: URGENCIA | R158: MINI GRANJAS | S158: 0742 | T158: Obra civil (concreto, agregados)
A159: 46105.603 | B159: 2372 | C159: 1812 | D159: CERRADA | E159: PAGADA | F159: Set (Electrico) Suministro | G159: (Sin Subgrupo) | H159: SERVICIO DE TRANSPORTE - UND | I159: 1 | J159: 625000 | K159: 625000 | L159: IVA 19% | M159: 0 | N159: =K159+M159 | O159: LAURA SOFIA SALAS ROSERO | P159: AWA INGENIERIA LTDA | Q159: PLANEADA | R159: MINI GRANJAS | S159: AWA-20263175 | T159: Viáticos - Transporte
A160: 46105.603 | B160: 2372 | C160: 1812 | D160: CERRADA | E160: PAGADA | F160: Set (Electrico) Suministro | G160: (Sin Subgrupo) | H160: CELDA PARA TRANSFORMADOR SECO DE 1250 KVA CLASE H 13.2KV - UND | I160: 1 | J160: 10290000 | K160: 10290000 | L160: IVA 19% | M160: 1955100 | N160: =K160+M160 | O160: LAURA SOFIA SALAS ROSERO | P160: AWA INGENIERIA LTDA | Q160: PLANEADA | R160: MINI GRANJAS | S160: AWA-20263175 | T160: Transformadores y celdas
A161: 46099.636 | B161: 2338 | C161: 1762 | D161: GENERADA | E161: PAGADA | F161: Servicio | G161: Upme | H161: CERTIFICADO UPME - UND | I161: 1 | J161: 7843530 | K161: 7843530 | M161: 0 | N161: =K161+M161 | O161: LAURA SOFIA SALAS ROSERO | P161: UNIDAD DE PLANEACION MINERO ENERGETICA (UPME) | Q161: PLANEADA | R161: MINI GRANJAS | T161: RETIE / Legalización / Medición
A162: 46099.635 | B162: 2337 | C162: 1770 | D162: CERRADA | E162: PAGADA | F162: Servicio | G162: Baños Portátiles | H162: ALQUILER DE LAVAMANOS PORTATIL - UND | I162: 1 | J162: 40000 | K162: 40000 | M162: 0 | N162: =K162+M162 | O162: LAURA SOFIA SALAS ROSERO | P162: HOOVER ANTONIO GUACHAVES LASSO | Q162: PLANEADA | R162: MINI GRANJAS | S162: 018 | T162: Baños y sanitarios portátiles
A163: 46099.635 | B163: 2337 | C163: 1770 | D163: CERRADA | E163: PAGADA | F163: Servicio | G163: Baños Portátiles | H163: ALQUILER DE BAÑO PORTATIL - UND | I163: 1 | J163: 1681600 | K163: 1681600 | M163: 0 | N163: =K163+M163 | O163: LAURA SOFIA SALAS ROSERO | P163: HOOVER ANTONIO GUACHAVES LASSO | Q163: PLANEADA | R163: MINI GRANJAS | S163: 018 | T163: Baños y sanitarios portátiles
A164: 46097.52 | B164: 2306 | C164: 1721 | D164: CERRADA | E164: PAGADA | F164: Armado Mesas Fv | G164: (Sin Subgrupo) | H164: ALQUILER MEZCLADORA X DÍA - UND | I164: 37 | J164: 45135 | K164: 1669995 | M164: 0 | N164: =K164+M164 | O164: LAURA SOFIA SALAS ROSERO | P164: GLADIS MARGOTH ARTEAGA | Q164: PLANEADA | R164: MINI GRANJAS | S164: 005 | T164: Alquiler de maquinaria y equipos
A165: 46097.474 | B165: 2294 | C165: 1719 | D165: CERRADA | E165: PAGADA | F165: Servicio | G165: Preparativos Previos Inicio De Obras | H165: ALQUILER RETROEXCAVADORA - UND | I165: 1 | J165: 38903000 | K165: 38903000 | M165: 0 | N165: =K165+M165 | O165: LAURA SOFIA SALAS ROSERO | P165: FAINCO SAS | Q165: PLANEADA | R165: MINI GRANJAS | S165: Nº FE-538 | T165: Alquiler de maquinaria y equipos
A166: 46086.396 | B166: 2182 | C166: 1651 | D166: CERRADA | E166: PAGADA | F166: Servicio | G166: Logística Viáticos | H166: SERVICIO DE RESTAURANTE - UND | I166: 67 | J166: 10362 | K166: 694254 | M166: 0 | N166: =K166+M166 | O166: JULIO CESAR DEAVILA MARTINEZ | P166: MAYERLINE TOBAR GOMEZ | Q166: URGENCIA | R166: MINI GRANJAS | S166: FE1522 | T166: Viáticos - Alimentación
...
